[
  {
    "id": "045",
    "name": "大神神社",
    "読み": "おおみわじんじゃ",
    "旧国": "大和国",
    "都道府県": "奈良県",
    "住所": "奈良県桜井市三輪1422",
    "緯度": 34.528747,
    "経度": 135.852066,
    "創建": "伝：崇神天皇の御代（紀元前97年頃）に現在地に祭祀が確立したと伝えられる。史書上の最古記録は『日本書紀』崇神天皇7年条（大物主神が大田田根子に祀られることを命じた記事）。三輪山信仰そのものは縄文・弥生時代まで遡ると考えられる。",
    "主祭神": "大物主大神（おおものぬしのおおかみ）",
    "配祀神": [
      "大己貴神（おおなむちのかみ）",
      "少彦名神（すくなひこなのかみ）"
    ],
    "ご利益": [
      "縁結び",
      "夫婦円満",
      "病気平癒",
      "醸造・食物守護",
      "農業守護",
      "厄除け",
      "開運全般"
    ],
    "開運キーワード": "日本最古の神が宿る山そのものへの祈り――心身の根っこを整える聖地",
    "開運フード": {
      "name": "三輪そうめん（手延べそうめん流し）",
      "店または場所": "そうめん處 森正（もりしょう）／JR三輪駅すぐ、大神神社参道入口の老舗。夏期限定でそうめん流しを提供。TEL 0744-43-7411",
      "効能": "三輪そうめんは約1300年前、大物主大神の神意によって生まれた日本最古のそうめん発祥地の名物。三輪山の伏流水で練られた極細の麺は「神の食べ物」ともいわれる。",
      "エピソード": "狭井神社の薬井戸から湧く「くすり水」（神水）も名物。参拝後に境内の薬水をペットボトルに汲む女性参拝者が後を絶たない。三輪山の伏流水は万病に効くとされ古来より「神の水」として珍重されてきた。1660年創業・今西酒造の銘酒「三諸杉（みむろすぎ）」も三輪山の伏流水を使う。（桜井市観光協会公式HP・三輪素麺振興会公式HP参照）"
    },
    "必買お守り": [
      {
        "name": "源気うさぎ守（げんきうさぎまもり）",
        "初穂料": "1,000円",
        "特徴": "大神神社独自のうさぎを象った守り。大物主大神の使いは白蛇（巳）だが、大和の国では兎も縁起の使いとして親しまれており、源気（元気）回復・開運に。インスタ映えするデザインで女性参拝者に絶大な人気。大神神社公式サイト授与品ページ記載。",
        "どんな人向け": "体力・気力を回復したい人、前向きに物事を進めたい人"
      },
      {
        "name": "縁結うさぎ守（えんむすびうさぎまもり）",
        "初穂料": "800円",
        "特徴": "縁結びの御神徳を宿したうさぎ形のお守り。大物主大神は「縁結び」の神としても信仰され、古事記の「大国主神（大物主大神の別称）」が数多くの縁結びの神話を持つことから来る。大神神社公式サイト記載。",
        "どんな人向け": "良縁を求める女性、人間関係の改善を願う人"
      },
      {
        "name": "病気平癒守（びょうきへいゆまもり）",
        "初穂料": "社務所にて（要現地確認）",
        "特徴": "大物主大神は疫病を鎮めた医薬の神としての側面を持ち、摂社・狭井神社の薬井戸の神水とともに病気平癒を願う参拝者に授与される。大神神社公式サイト・授与品ページ参照。",
        "どんな人向け": "病気療養中の人、家族の健康を祈る人"
      },
      {
        "name": "なでうさぎ土鈴（なでうさぎどれい）",
        "初穂料": "800円",
        "特徴": "参集殿の「なでうさぎ（撫で兎）」は、撫でると運気が上がり、身体の痛みも取ってくれると伝わる。その兎を象った土鈴のお守り。大神神社公式サイト記載。",
        "どんな人向け": "神社グッズ好きの女性、体の不調を抱える人"
      }
    ],
    "秘密の話": [
      {
        "title": "本殿を持たない「三輪山そのものが御神体」という原初の祭祀形態",
        "内容": "大神神社には本殿がなく、拝殿奥の「三ツ鳥居」を通して三輪山（標高467m）に向かって参拝する。山中には奥津磐座・中津磐座・辺津磐座の3つの磐座があり、神々が宿る場所とされる。これは日本最古の神祀りの様式であり、「本殿のない神社」として全国でも極めて稀。山中への登拝は今も可能だが、飲食禁止・写真撮影禁止・午後2時以降の入山禁止という厳しい制約がある。",
        "ソース": "大神神社公式サイト（oomiwa.or.jp）三輪山ページ・境内マップ; Wikipedia「大神神社」"
      },
      {
        "title": "巳の神杉（みのかみすぎ）に供えられる卵とお神酒",
        "内容": "拝殿の西側に「巳の神杉」と呼ばれる樹齢500年ともいわれる御神木があり、大物主大神の化身である白蛇が棲むとされる。参拝者が卵やお神酒を供える慣習が続き、今も卵の殻が積み重なっている光景が見られる。大物主大神が白蛇に化けて美女のもとに通ったという古事記の神話（三輪山伝説）が起源。",
        "ソース": "大神神社公式サイト「巳の神杉」ページ（oomiwa.or.jp）; 『古事記』大物主神話"
      },
      {
        "title": "狭井神社の薬井戸から湧く「くすり水」は万病に効く神水",
        "内容": "大神神社の摂社・狭井神社（正式名称：狭井坐大神荒魂神社）の境内に、三輪山を水源とする霊水「薬井戸」がある。この水は古来「くすり水」と呼ばれ、万病に効くと信仰されてきた。参拝者が自由に汲むことができ、ペットボトル持参の女性参拝者が列をなすことも。境内には古代の薬草園もある。",
        "ソース": "大神神社公式サイト「狭井神社」ページ（oomiwa.or.jp）; 奈良県観光公式サイト「あをによし なら旅ネット」"
      }
    ],
    "女性人気ポイント": "うさぎのお守りとなでうさぎがSNSで人気沸騰。三輪山を背景にした二の鳥居の写真は奈良随一のフォトスポット。狭井神社の薬井戸の神水を汲む体験は「体の中から浄化される」と評判。三輪そうめん発祥の地として食の楽しみもあり、御朱印は「大神神社」「摂社狭井神社」など複数社で集められる。",
    "参拝情報": {
      "最寄り駅": "JR桜井線「三輪駅」より徒歩約5分。JR奈良駅から約25分（直通）、大阪・鶴橋駅から近鉄・桜井経由で約40分。",
      "駐車場": "有料駐車場あり（神社東側・普通車500円程度）。初詣時期は混雑するため電車利用推奨。",
      "授与所受付時間": "9:00〜16:00（社務所・授与所）",
      "御朱印初穂料": "500円（大神神社本社）。摂社各社でも授与。"
    },
    "公式URL": "https://oomiwa.or.jp/",
    "参拝所要時間": "60〜90分（狭井神社・薬井戸・なでうさぎ巡りを含む）。三輪山登拝は別途2〜3時間。",
    "ベストシーズン": {
      "春": "3〜4月の桜と新緑。拝殿前の「御神木の桜」と若葉の三輪山が美しい。",
      "夏": "7月下旬の「夏越の大祓」。蒸し暑いが参道の木陰で涼める。三輪そうめん流しのシーズン（森正）。",
      "秋": "10〜11月の紅葉。山の辺の道と組み合わせた秋の一人旅が特に人気。",
      "冬": "1月の初詣は全国から多くの参拝者。1月のみそぎまつりも有名。"
    },
    "セット参拝コース": [
      "山の辺の道コース：大神神社→檜原神社（三輪山の麓）→石上神宮（約13km徒歩）",
      "大和の古社三社コース：大神神社→談山神社（タクシー）→長谷寺（電車）",
      "奈良一の宮セット：大神神社（大和国）→春日大社（徒歩エリア違うが同日可能・電車で約40分）"
    ],
    "一人旅アクセス": {
      "電車のみで完結可": true,
      "駅から徒歩可": true,
      "最終アクセス難易度": "易",
      "女性一人歩き安全性コメント": "三輪駅から境内まで5分の平坦な参道。日中は参拝者多数で安心。山の辺の道ハイキングは昼間のみ推奨。"
    }
  },
  {
    "id": "046",
    "name": "枚岡神社",
    "読み": "ひらおかじんじゃ",
    "旧国": "河内国",
    "都道府県": "大阪府",
    "住所": "大阪府東大阪市出雲井町7番16号",
    "緯度": 34.67715,
    "経度": 135.6805,
    "創建": "伝：神武天皇即位前3年（紀元前660年頃）、中臣氏の祖・天種子命が神津嶽（かみつだけ）の頂上に天児屋根命を祀ったのが起源と伝えられる。史書上は『続日本紀』文武天皇元年（697年）に朝廷から神封が贈られた記録が最古。",
    "主祭神": "天児屋根命（あめのこやねのみこと）",
    "配祀神": [
      "比売御神（ひめみかみ）",
      "武甕槌命（たけみかづちのみこと）",
      "経津主命（ふつぬしのみこと）"
    ],
    "ご利益": [
      "縁結び",
      "夫婦円満",
      "安産",
      "厄除け",
      "家内安全",
      "勝負運",
      "仕事運"
    ],
    "開運キーワード": "言霊の神・祝詞の神に言葉の力を授けてもらう。伝えたい想いを神前で声に出すと叶いやすくなる",
    "開運フード": {
      "name": "あられ・おかき（東大阪の老舗米菓）",
      "店または場所": "参道周辺の土産店・生駒山系の麓エリア各店。東大阪市内には米菓の製造業者が多く、参道土産として販売されている。",
      "効能": "お米を神前に供える風習から、米菓は神聖な食とされる。神前に供えられた米の霊力が宿るとされる縁起物。",
      "エピソード": "枚岡神社は「元春日」とも称され、春日大社（奈良）とは兄弟社の関係。春日大社でも神鹿が有名なように、枚岡神社の生駒山系も自然豊かで、初秋には「しめ縄作り体験」も行われる。社務所で授与されるお守りを求めて平日も参拝者が訪れる。"
    },
    "必買お守り": [
      {
        "name": "縁結守（えんむすびまもり）",
        "初穂料": "社務所にて（要現地確認）",
        "特徴": "天児屋根命は「言霊の神・祝詞の神」として縁結びにも効力があるとされる。枚岡神社独自デザインの縁結び守り。",
        "どんな人向け": "良縁・復縁を願う女性"
      },
      {
        "name": "厄除守（やくよけまもり）",
        "初穂料": "社務所にて（要現地確認）",
        "特徴": "春日大社の御祭神4柱のうち2柱が枚岡神社から勧請されたという由縁から、奈良・春日と同等の格式を持つ厄除けの御守り。旧官幣大社の格式。",
        "どんな人向け": "厄年の人、人生の節目を控えた人"
      },
      {
        "name": "笑いの御守（わらいのおまもり）",
        "初穂料": "社務所にて（要現地確認）",
        "特徴": "枚岡神社は毎年12月の「お笑い神事」で有名。参拝者全員が一斉に大笑いする全国的にも珍しい神事が行われ、笑いで福を呼ぶ御守りが授与される。枚岡神社公式サイト（hiraoka-jinja.org）記載。",
        "どんな人向け": "明るく前向きに生きたい人、運気を上げたい人全般"
      }
    ],
    "秘密の話": [
      {
        "title": "春日大社の「元社」——奈良の大社より古い大阪の一の宮",
        "内容": "奈良の春日大社（768年創建）は、枚岡神社の御祭神・天児屋根命と比売御神の2柱の分霊を「元春日」である枚岡神社から奈良に勧請して成立した。春日大社の方が後発であり、全国的に有名な春日大社より枚岡神社の方が歴史が古い。「元春日（もとかすが）」の称号はその証。",
        "ソース": "枚岡神社公式サイト（hiraoka-jinja.org）由緒ページ; 東大阪市観光ガイド（osaka-info.jp）"
      },
      {
        "title": "12月の「お笑い神事」——全国唯一・境内全員で大笑いする神事",
        "内容": "毎年12月23日に行われる「お笑い神事」では、神職が「さあ笑え、笑え」と発声すると、境内に集まった参拝者全員が一斉に大笑いする。笑い声で神様を喜ばせて新年の福を招く全国的にも珍しい神事で、テレビ・メディアにも多数取り上げられている。",
        "ソース": "東大阪市公式観光サイト（osaka-info.jp）; 枚岡神社公式サイト年間行事ページ"
      },
      {
        "title": "神武天皇即位前から続く聖域「神津嶽」の原始林",
        "内容": "現社殿より上方の生駒山腹には「神津嶽（かみつだけ）」と呼ばれる原始祭祀の地があり、神武天皇即位前3年に天種子命が天児屋根命を祀った最初の磐座が残る。現在も神津嶽本宮への登拝道があり、奥宮参拝コースとして知られる。",
        "ソース": "枚岡神社公式サイト「神津嶽」ページ（hiraoka-jinja.org）; note記事「神武天皇ゆかりの神域『神津嶽』と枚岡神社」"
      }
    ],
    "女性人気ポイント": "生駒山を背景にした朱色の社殿が映え写真スポット。12月の「お笑い神事」は女性グループ参拝にも人気。授与所のお守りは種類豊富で、縁結び・安産・厄除けと節目ごとのニーズに対応。御朱印は直書き対応。大阪都市部から近鉄電車1本でアクセスできる利便性も高い。",
    "参拝情報": {
      "最寄り駅": "近鉄奈良線「枚岡駅」より徒歩約2分（駅のすぐ前に一の鳥居）。大阪・難波駅から急行で約20分。",
      "駐車場": "境内東側に無料駐車場あり（台数限定）。",
      "授与所受付時間": "9:00〜17:00",
      "御朱印初穂料": "300円（通常）"
    },
    "公式URL": "http://hiraoka-jinja.org/",
    "参拝所要時間": "30〜60分（神津嶽本宮への登拝は別途40分）",
    "ベストシーズン": {
      "春": "3〜4月の桜。生駒山麓の桜と朱塗りの社殿のコントラストが美しい。",
      "夏": "緑豊かな参道の木陰が心地よい。",
      "秋": "11月の紅葉。生駒山の紅葉と社殿の朱色が見事。",
      "冬": "12月23日の「お笑い神事」は必見。正月初詣も賑わう。"
    },
    "セット参拝コース": [
      "河内国4社巡り：枚岡神社→（電車）→住吉大社→（電車）→坐摩神社→大鳥大社（1日コース）",
      "奈良ルート：枚岡神社→（近鉄）→春日大社・元春日の歴史を辿るコース"
    ],
    "一人旅アクセス": {
      "電車のみで完結可": true,
      "駅から徒歩可": true,
      "最終アクセス難易度": "易",
      "女性一人歩き安全性コメント": "駅から境内まで2分と極めて近く、日中は安全。生駒山への登拝は明るい時間帯のみ推奨。"
    }
  },
  {
    "id": "047",
    "name": "大鳥大社",
    "読み": "おおとりたいしゃ",
    "旧国": "和泉国",
    "都道府県": "大阪府",
    "住所": "大阪府堺市西区鳳北町1丁目1-2",
    "緯度": 34.5581,
    "経度": 135.4887,
    "創建": "伝：景行天皇43年（113年）に日本武尊の霊が白鳥となってこの地に降り立ち、社が建てられたとされる。史書上は延長5年（927年）の『延喜式神名帳』に名神大社として記載。",
    "主祭神": "日本武尊（やまとたけるのみこと）",
    "配祀神": [
      "大鳥連祖神（おおとりのむらじおやがみ）"
    ],
    "ご利益": [
      "勝負運・開運",
      "厄除け",
      "交通安全",
      "縁結び",
      "武運長久",
      "心願成就"
    ],
    "開運キーワード": "不死鳥のように何度でも甦る力——白鳥伝説の神が逆境を乗り越える勇気を授ける",
    "開運フード": {
      "name": "堺の白みそ雑煮・みたらし団子",
      "店または場所": "鳳参道周辺の和菓子店・茶屋。JR鳳駅周辺の和菓子店数店が参拝後の立ち寄りスポット。",
      "効能": "白鳥（白）にちなんだ白みそや白い食べ物は大鳥大社の縁起物とされる。",
      "エピソード": "全国に約400社ある大鳥神社・大鳥信仰の総本社。日本武尊が白鳥となってこの地に降り立ったという神話から「白鳥の地」として崇められる。境内の大楠（樹齢数百年）は大阪府の天然記念物に指定されており、パワースポットとして女性参拝者に人気。"
    },
    "必買お守り": [
      {
        "name": "先が見通せる御守（さきがみとおせるおまもり）",
        "初穂料": "社務所にて（要現地確認）",
        "特徴": "「先が見通せる」という名称で日本初のユニークなお守り。将来への不安を払い、先を見通す力を授けるとされる。大鳥大社公式サイト・授与品ページ記載。",
        "どんな人向け": "将来の方向性に迷っている人、転職・進路変更を考えている人"
      },
      {
        "name": "開運勝守（かいうんかちまもり）",
        "初穂料": "社務所にて（要現地確認）",
        "特徴": "日本武尊の「東西の征伐で勝ち続けた英雄神」としての御神徳を宿す勝運お守り。スポーツ・受験・仕事の勝負に。",
        "どんな人向け": "何かに挑戦中の人、勝負の年を控えた人"
      },
      {
        "name": "縁結守（えんむすびまもり）",
        "初穂料": "社務所にて（要現地確認）",
        "特徴": "日本武尊は複数の妻・恋人との神話を持つことから縁結びの御神徳もある。和泉国一の宮の格式を持つお守り。",
        "どんな人向け": "良縁を求める女性全般"
      }
    ],
    "秘密の話": [
      {
        "title": "日本武尊の魂が3か所を経由してこの地に留まった「白鳥飛翔伝説」",
        "内容": "日本武尊は伊吹山で病に倒れ三重の能褒野で薨去したが、陵墓から白鳥となって大和（古市）→河内（古市）→大鳥（堺）と3か所を経由して最終的にこの地に留まったとされる。『日本書紀』に記されたこの伝説から、大鳥の地名が生まれ、全国の大鳥神社の総本社となった。白鳥が「不死・再生」の象徴であることから「何度でも甦る力を授ける神」として信仰が厚い。",
        "ソース": "『日本書紀』景行天皇紀; 大鳥大社公式サイト「由緒」（ootoritaisha.jp）; Wikipedia「大鳥大社」"
      },
      {
        "title": "全国約400社・大鳥神社の総本社という格式",
        "内容": "全国に点在する「大鳥神社」「鳳神社」などの社は、すべて大鳥大社を総本社とする。日本武尊信仰の根本として、江戸時代には徳川幕府からも崇敬を受け、社殿が整備された歴史がある。現在も全国から日本武尊ゆかりの神社参拝者が訪れる。",
        "ソース": "大鳥大社公式サイト（ootoritaisha.jp）; 神社ラボ「大鳥大社の由緒」"
      },
      {
        "title": "「先が見通せるおみくじ」は日本初の名称・コンセプト",
        "内容": "大鳥大社が授与する「先が見通せるおみくじ」と「先が見通せる御守」は、その名称と「先を見通す力を授ける」というコンセプトが日本初とされ、全国的に注目された。将来への不安を抱える現代人のニーズに応えた独自の発想が女性参拝者の共感を呼んでいる。",
        "ソース": "大鳥大社公式サイト授与品ページ（ootoritaisha.jp）; 神社ラボ「大鳥大社」記事"
      }
    ],
    "女性人気ポイント": "「先が見通せる御守」はSNSで話題になり全国からの参拝者を集める。境内の大楠（大阪府天然記念物）のもとでパワーチャージする女性が多い。白鳥の神様にちなんだ「再生・甦り」の御神徳は、人生の転機を迎えた女性に響く。御朱印はシンプルながら格調のあるデザイン。",
    "参拝情報": {
      "最寄り駅": "JR阪和線「鳳（おおとり）駅」より徒歩約10分。大阪・天王寺駅から快速で約15分。",
      "駐車場": "境内南側に無料駐車場あり。",
      "授与所受付時間": "9:00〜16:30",
      "御朱印初穂料": "300円"
    },
    "公式URL": "https://www.ootoritaisha.jp/",
    "参拝所要時間": "30〜45分",
    "ベストシーズン": {
      "春": "4月の「大鳥大社春季大祭」。参道の桜が咲く頃が美しい。",
      "夏": "境内の大楠の緑が濃くなる夏の木陰参拝が心地よい。",
      "秋": "10月の秋祭り。だんじり文化の堺エリアで祭り文化も楽しめる。",
      "冬": "静寂の中での初詣。大社の格調ある雰囲気が際立つ。"
    },
    "セット参拝コース": [
      "和泉・摂津巡り：大鳥大社→（電車30分）→住吉大社→坐摩神社（大阪4社1日コース）",
      "堺観光セット：大鳥大社→仁徳天皇陵（世界遺産）→堺市内グルメ"
    ],
    "一人旅アクセス": {
      "電車のみで完結可": true,
      "駅から徒歩可": true,
      "最終アクセス難易度": "易",
      "女性一人歩き安全性コメント": "駅から10分の住宅街を歩くルート。日中は安全で分かりやすい道。"
    }
  },
  {
    "id": "048",
    "name": "住吉大社",
    "読み": "すみよしたいしゃ",
    "旧国": "摂津国",
    "都道府県": "大阪府",
    "住所": "大阪府大阪市住吉区住吉2丁目9-89",
    "緯度": 34.6133,
    "経度": 135.4931,
    "創建": "伝：神功皇后摂政11年（211年）、神功皇后が三韓からの凱旋後に住吉大神を奉斎したのが起源。史書上は『日本書紀』神功皇后摂政11年条に記録あり。現本殿は文化7年（1810年）に再建。",
    "主祭神": "底筒男命（そこつつのおのみこと）・中筒男命（なかつつのおのみこと）・表筒男命（うわつつのおのみこと）の住吉三神",
    "配祀神": [
      "神功皇后（じんぐうこうごう）"
    ],
    "ご利益": [
      "和歌・芸能の神",
      "航海安全",
      "縁結び",
      "夫婦円満",
      "安産",
      "商売繁昌",
      "開運招福",
      "勝負運"
    ],
    "開運キーワード": "200万人が初詣に訪れる大阪最強の総鎮守——「発達」を約束する初辰まいりで運気を積み重ねる",
    "開運フード": {
      "name": "縁起焼き（えんきやき）",
      "店または場所": "住吉大社門前・参道周辺の和菓子店。「良いご縁が起きますように」の願いを込めてあんこ・よもぎ・カスタードを包んで丸く焼いた縁起菓子。",
      "効能": "「縁起」の名を冠する縁起物の和菓子。参拝のお土産として喜ばれる。",
      "エピソード": "住吉大社は全国2,300社の住吉神社総本社。毎年の初詣参拝者は約200万人と全国屈指。参道には老舗の和菓子屋・飲食店が並び、おはぎ・みたらし団子・縁起焼きが参拝後の定番グルメ。境内敷地は約5.8万坪と広大。（住吉大社公式サイト・大阪府観光サイト参照）"
    },
    "必買お守り": [
      {
        "name": "五大力石御守（ごだいりきいしおまもり）",
        "初穂料": "初穂料500円（お守り袋）＋石は境内・五所御前で自分で探す",
        "特徴": "第一本宮南側の「五所御前」の玉砂利の中から「五」「大」「力」と書かれた3つの小石を自分で探し出し、授与所で求めた御守り袋に入れて持ち歩く。五大力（体力・智力・財力・福力・寿命力）が授かるとされる、住吉大社独自の体験型お守り。住吉大社公式サイト記載。",
        "どんな人向け": "ゲーム感覚で神社体験をしたい人、総合的な運気アップを願う人"
      },
      {
        "name": "初辰招福猫（はつたつしょうふくねこ）",
        "初穂料": "社務所にて（要現地確認・毎月初辰の日に授与）",
        "特徴": "毎月の「初辰まいり」で楠珺社にて授与される招き猫。奇数月は左手（人招き・家内安全）、偶数月は右手（金招き・商売繁昌）の招き猫で、48体（4年分）集めると「始終発達（しじゅうはったつ）」が完成するとされる。住吉大社公式サイト「楠珺社」ページ記載。",
        "どんな人向け": "長期的な運気アップ・商売繁昌を願う人、招き猫コレクター"
      },
      {
        "name": "おもと人形（縁結び）",
        "初穂料": "1,000円",
        "特徴": "縁結びの御守り人形。住吉大社では縁結び・夫婦円満も御神徳のひとつ。住吉大社公式サイト授与品ページ記載。",
        "どんな人向け": "良縁を求める女性、夫婦の絆を深めたい人"
      }
    ],
    "秘密の話": [
      {
        "title": "太鼓橋（反橋）を淀君が寄進した理由——秀吉の子・秀頼の成長祈願",
        "内容": "住吉大社の象徴・反橋（太鼓橋）は、豊臣秀吉の側室・淀君が息子・豊臣秀頼の成長祈願のために奉納したと伝わる。急勾配の橋（傾斜約48度）を渡ることで罪や穢れが祓われるとされ、渡るだけで厄除けになるという信仰が続く。現在の橋は元禄年間（1688〜1704年）に再建されたもの。",
        "ソース": "住吉大社公式サイト「反橋」ページ（sumiyoshitaisha.net）; JR東海ツアーズ「住吉大社完全ガイド」"
      },
      {
        "title": "「初辰まいり」4年・48体で「始終発達」——商売人が代々続けてきた独自信仰",
        "内容": "毎月の「初辰の日」に境内の4社（南海大神・種貸社・楠珺社・浅澤社・大歳社）をお参りし、招き猫を1体ずつ集めて4年間（48ヶ月）続けると「始終（4年間）発達（48体）」が完成するという、住吉大社独自の長期参拝システム。江戸時代から大阪の商売人が続けてきた慣わしで、今も毎月数千人が参拝する。",
        "ソース": "住吉大社公式サイト「初辰まいり」ページ（sumiyoshitaisha.net）; 住吉大社インタビュー記事（okumiya-jinja.com）"
      },
      {
        "title": "4棟すべてが国宝の本殿——「住吉造」は伊勢神宮・出雲大社と並ぶ日本最古の建築様式",
        "内容": "第一本宮から第四本宮までの4棟の本殿はすべて文化7年（1810年）建造の国宝建造物。「住吉造（すみよしづくり）」と称する建築様式は、切妻造・妻入・直線的な屋根が特徴で、伊勢神宮の「神明造」・出雲大社の「大社造」と並ぶ日本三古式のひとつ。4棟が直線上に並ぶ配置も世界的に見て珍しい。",
        "ソース": "住吉大社公式サイト「本殿」ページ（sumiyoshitaisha.net）; 文化庁「国宝・重要文化財（建造物）住吉大社本殿」"
      }
    ],
    "女性人気ポイント": "五大力石探しは女友達・カップルでの参拝に大人気。太鼓橋の美しいアーチは定番フォトスポット。初辰まいりの招き猫コレクションはじわじわ人気が広がっている。御朱印は4本宮それぞれで授与でき、御朱印コレクターにも絶大な人気。大阪の中心部から南海電鉄で15分というアクセスの良さも魅力。",
    "参拝情報": {
      "最寄り駅": "南海本線「住吉大社駅」より徒歩約3分、または阪堺電車「住吉鳥居前駅」すぐ。大阪・難波駅から南海急行で約10分。",
      "駐車場": "境内東側に有料駐車場あり。初詣時期は激混みのため電車推奨。",
      "授与所受付時間": "9:00〜17:00（通常時）",
      "御朱印初穂料": "300円（各本宮）"
    },
    "公式URL": "https://www.sumiyoshitaisha.net/",
    "参拝所要時間": "60〜90分（4本宮＋五所御前＋楠珺社の初辰まいりルートを含む）",
    "ベストシーズン": {
      "春": "3〜4月の桜と菜の花。境内の池泉式庭園・住吉公園との組み合わせが美しい。",
      "夏": "7月の「住吉祭（すみよしまつり）」は大阪三大夏祭りのひとつ。神輿の川渡りが圧巻。",
      "秋": "10〜11月の七五三参りシーズン。秋の境内は落ち着いた雰囲気。",
      "冬": "1月の初詣は全国でもトップクラスの参拝者数（約200万人）。年越しの雰囲気が格別。"
    },
    "セット参拝コース": [
      "摂津国2社巡り：住吉大社→（電車30分）→坐摩神社（本町）",
      "大阪4社1日コース：住吉大社→坐摩神社→枚岡神社→大鳥大社"
    ],
    "一人旅アクセス": {
      "電車のみで完結可": true,
      "駅から徒歩可": true,
      "最終アクセス難易度": "易",
      "女性一人歩き安全性コメント": "大阪都市部の住宅地に鎮座。駅直結で境内まで3分。日中は常に参拝者がいて安心。夜間の参拝は避けることを推奨。"
    }
  },
  {
    "id": "049",
    "name": "坐摩神社",
    "読み": "いかすりじんじゃ",
    "旧国": "摂津国",
    "都道府県": "大阪府",
    "住所": "大阪市中央区久太郎町4丁目渡辺3号",
    "緯度": 34.6829,
    "経度": 135.5015,
    "創建": "伝：神功皇后摂政元年（200年頃）、新羅からの御帰還の際に現在の天満橋西方・渡辺の地に坐摩大神を奉斎したのが起源とされる。史書上は『延喜式神名帳』（927年）に摂津国一宮として記載。現在地への遷座は天正11年（1583年）、豊臣秀吉の大坂城築城に伴うもの。",
    "主祭神": "生井神（いくいのかみ）・福井神（さくいのかみ）・綱長井神（つながいのかみ）・波比祇神（はひきのかみ）・阿須波神（あすはのかみ）の五柱（総称：坐摩神）",
    "配祀神": [
      "騎牛天満宮（きぎゅうてんまんぐう）",
      "相殿社に陶器神社・繊維神社ほか複数"
    ],
    "ご利益": [
      "住居守護・地鎮",
      "旅行安全",
      "安産・育児守護",
      "商売繁昌",
      "縁結び"
    ],
    "開運キーワード": "ビジネス街のど真ん中に鎮座する都会の一の宮——「住まい」と「旅」の守り神に仕事と家庭の両立を祈る",
    "開運フード": {
      "name": "大阪の陶器まつり名物・境内屋台（7月）",
      "店または場所": "坐摩神社境内・境内陶器神社の「陶器まつり」（毎年7月下旬〜8月初旬）。境内に陶器商が集まり、境内屋台も並ぶ。",
      "効能": "陶器神社は全国の陶芸・焼き物の守り神。陶器まつり期間中は100軒以上の出店があり、焼き物を新調すると「縁起が良い」とされる。",
      "エピソード": "坐摩神社は大阪・本町のビジネス街に鎮座するユニークな一の宮。境内には陶器神社・繊維神社・相殿社など多数の末社があり「摂津の総社」的役割を持つ。「渡辺」姓の発祥の地としても有名で、全国の渡辺・渡部・渡邊姓の人が参拝に訪れる。（坐摩神社公式サイト・大阪観光局参照）"
    },
    "必買お守り": [
      {
        "name": "住居守護のお守り（じゅうきょしゅごのおまもり）",
        "初穂料": "社務所にて（要現地確認）",
        "特徴": "坐摩大神の主なご神徳「住居の守護」を宿す。引越し・新築・家内安全に強いお守り。全国的にも住居守護専門の一の宮は珍しい。",
        "どんな人向け": "引越し・新居・新婚の人"
      },
      {
        "name": "旅行安全守（りょこうあんぜんまもり）",
        "初穂料": "社務所にて（要現地確認）",
        "特徴": "坐摩大神は旅行安全の御神徳でも有名。一人旅の女性参拝者に特に人気。",
        "どんな人向け": "旅好き・出張の多い人・一人旅をする女性"
      },
      {
        "name": "安産守（やすみまもり）",
        "初穂料": "社務所にて（要現地確認）",
        "特徴": "坐摩大神の御神徳のひとつ「安産・育児守護」を授かるお守り。妊婦・子授けを願う女性から根強い人気。",
        "どんな人向け": "妊婦・子授けを願う女性"
      }
    ],
    "秘密の話": [
      {
        "title": "豊臣秀吉の大坂城築城で「渡辺の地」から強制移転——全国「渡辺」姓発祥の地",
        "内容": "坐摩神社はもともと天満橋西方の「渡辺の地（渡辺津）」に鎮座していたが、天正11年（1583年）に豊臣秀吉が大坂城を築城する際に現在地へ移転させられた。この「渡辺の地」が「渡辺」「渡部」「渡邊」姓の発祥とされ、全国数十万人の渡辺姓が参拝に訪れる。",
        "ソース": "坐摩神社公式サイト由緒ページ; 大阪観光局「坐摩神社ガイド」（osaka-info.jp）"
      },
      {
        "title": "三ツ鳥居——伊勢神宮・三輪大社と並ぶ全国三例のみの珍しい鳥居",
        "内容": "境内入口には「三ツ鳥居（みつとりい）」と呼ばれる、3つの鳥居が横に並んだ珍しい形式の鳥居が建つ。全国でも伊勢神宮・大神神社（奈良）・坐摩神社の3か所にしか現存しないとされる。この形式は神聖さの度合いを示すもので、坐摩神社の格式の高さを象徴している。",
        "ソース": "坐摩神社公式サイト（神社本庁別表神社）; spiritualjapan.net「坐摩神社」記事"
      },
      {
        "title": "ビジネス街に鎮座する「都会の一の宮」——昼休みに参拝するサラリーマン・OLの文化",
        "内容": "大阪・本町（ほんまち）のビジネス街のど真ん中に鎮座する全国的にも珍しい一の宮。周囲はオフィスビルに囲まれており、昼休みに手を合わせるビジネスパーソンが絶えない。境内は日中でも静寂が保たれており、「都会のオアシス」として地元民に親しまれている。",
        "ソース": "大阪観光局公式サイト（osaka-info.jp）「坐摩神社」; フォートラベル「大阪ビジネス街の一之宮」記事"
      }
    ],
    "女性人気ポイント": "本町のカフェ・グルメと組み合わせた「ランチ参拝」に女性OLに人気。三ツ鳥居は珍しいフォトスポット。7月の陶器まつりは焼き物好きの女性に人気。御朱印はシンプルかつ格調あるデザイン。参拝後に本町・心斎橋のショッピングと組み合わせやすい立地。",
    "参拝情報": {
      "最寄り駅": "大阪メトロ四つ橋線・中央線・御堂筋線「本町駅」より徒歩約3分。",
      "駐車場": "境内に駐車場なし（近隣のコインパーキング利用）。",
      "授与所受付時間": "9:00〜17:00",
      "御朱印初穂料": "300円"
    },
    "公式URL": "https://www.ikasuri.or.jp/",
    "参拝所要時間": "20〜30分（末社巡りを含めて45分）",
    "ベストシーズン": {
      "春": "新年度の祈願（4月）に参拝するビジネスパーソンが多い。",
      "夏": "7月末〜8月初の「陶器まつり」は境内が賑わう。",
      "秋": "10月の秋季大祭。境内銀杏の黄葉が美しい。",
      "冬": "1月の初詣。都会の一の宮らしい凛とした雰囲気。"
    },
    "セット参拝コース": [
      "摂津国2社セット：坐摩神社（本町）→（地下鉄15分）→住吉大社",
      "大阪ビジネス街参拝：坐摩神社→難波神社（難波）→今宮戎神社（恵比寿）"
    ],
    "一人旅アクセス": {
      "電車のみで完結可": true,
      "駅から徒歩可": true,
      "最終アクセス難易度": "易",
      "女性一人歩き安全性コメント": "大阪中心のビジネス街で日中は安全。周辺はオフィスビルが立ち並び治安良好。"
    }
  },
  {
    "id": "050",
    "name": "日前神宮・國懸神宮",
    "読み": "ひのくまじんぐう・くにかかすじんぐう",
    "旧国": "紀伊国",
    "都道府県": "和歌山県",
    "住所": "和歌山県和歌山市秋月365",
    "緯度": 34.22789,
    "経度": 135.20239,
    "創建": "伝：神武天皇2年（紀元前659年）創祀。史書上は『日本書紀』神武天皇即位前紀に「紀国（きのくに）の奉斎神」として記録があり、日本最古の神社のひとつ。現社殿は明治時代に整備されたもの。",
    "主祭神": "【日前神宮】日前大神（ひのくまのおおかみ）—日像鏡（ひがたのかがみ）を御神体とする。【國懸神宮】國懸大神（くにかかすのおおかみ）—日矛鏡（ひぼこのかがみ）を御神体とする。",
    "配祀神": [
      "【日前神宮】思兼命（おもいかねのみこと）、石凝姥命（いしこりどめのみこと）",
      "【國懸神宮】玉祖命（たまのやのみこと）、明立天御影命（あけたつあめのみかげのみこと）、鈿女命（うづめのみこと）"
    ],
    "ご利益": [
      "縁結び",
      "日光の恩恵・太陽のパワー",
      "厄除け",
      "心願成就",
      "病気平癒",
      "国土安泰"
    ],
    "開運キーワード": "天照大御神に並ぶ2柱の太陽神——「鏡」の神様に自分自身の真の姿を映してもらう",
    "開運フード": {
      "name": "和歌山ラーメン（中華そば）",
      "店または場所": "神社から車で約10分の和歌山市内「井出商店（いでしょうてん）」（和歌山市田中町4-84）など。和歌山市内に名店多数。",
      "効能": "和歌山の「魂のソウルフード」として地元民が代々食べてきた郷土食。参拝後の食事として定番。",
      "エピソード": "日前神宮・國懸神宮は同一境内に2社が同格で鎮座する全国でも極めて珍しい形態。紀伊国の「神域」として2600年以上にわたり人々の信仰を集めてきた。境内は撮影制限があり、本殿への参拝も厳粛な雰囲気が漂う。（日前神宮・國懸神宮公式サイト参照）"
    },
    "必買お守り": [
      {
        "name": "えんむすびなかよしお守り",
        "初穂料": "社務所にて（要現地確認）",
        "特徴": "日前宮の縁結びのお守り。リボン形の可愛らしいデザインで女性参拝者に人気。公式サイト（hinokuma-jingu.com）記載。",
        "どんな人向け": "良縁を求める女性"
      },
      {
        "name": "願いが叶う鈴のお守り",
        "初穂料": "社務所にて（要現地確認）",
        "特徴": "鈴の音が邪気を祓うとされる縁起物。日前宮独自のお守り。公式サイト記載。",
        "どんな人向け": "心願成就・邪気払いを願う人"
      },
      {
        "name": "合格祈願守",
        "初穂料": "社務所にて（要現地確認）",
        "特徴": "日前大神・國懸大神の強い御神徳から合格祈願に参拝する受験生が多い。社務所にて授与。",
        "どんな人向け": "受験生・資格試験を控えた人"
      }
    ],
    "秘密の話": [
      {
        "title": "天照大御神に先立って作られた「2枚の鏡」を御神体とする——伊勢神宮より古い可能性",
        "内容": "日前大神の御神体「日像鏡」と國懸大神の御神体「日矛鏡」は、天照大御神を祀る八咫鏡（やたのかがみ・伊勢神宮御神体）よりも先に作られた鏡と伝わる。岩戸隠れ神話で最初に作られた鏡だが出来が悪く、やり直して作ったのが八咫鏡とされる。つまり日前宮の鏡は「日本最初に作られた鏡」であり、伊勢神宮の御神体の「試作品」であるという。",
        "ソース": "日前神宮・國懸神宮公式サイト（hinokuma-jingu.com）由緒ページ; Wikipedia「日前神宮・國懸神宮」"
      },
      {
        "title": "同一境内に2社が「同格・同権」で鎮座する全国唯一の形態",
        "内容": "日前神宮と國懸神宮は同一境内（鳥居も共有）の中に、向かい合わせで建てられている。2社はどちらが上位でもなく「対等・同格」の関係にあり、参拝順序は参拝者の自由。全国2,000社以上の一の宮の中でも、同格の2社が同一境内に並ぶのはこの社のみとされる。",
        "ソース": "日前神宮・國懸神宮公式サイト（hinokuma-jingu.com）; Wikipedia「日前神宮・國懸神宮」; 全国史跡巡りサイト"
      },
      {
        "title": "2600年以上変わらない「禁足地」——本殿は非公開で一般参拝者は入れない聖域",
        "内容": "日前神宮・國懸神宮の両本殿は、2,600年以上にわたって一般参拝者を立ち入らせない「禁足地（きんそくち）」として厳重に守られてきた。現在も本殿周囲は玉垣で囲まれており、遥拝のみが許されている。この「近づけない神聖さ」が逆に霊験あらたかさを伝えてきた。",
        "ソース": "日前神宮・國懸神宮公式サイト（hinokuma-jingu.com）; 和歌山市観光公式サイト"
      }
    ],
    "女性人気ポイント": "2社同格という全国唯一の形態が「神秘体験」として口コミで広まっている。可愛いリボン形の縁結びお守りが女性に人気。境内の静寂な雰囲気は都会の喧騒を忘れさせる。御朱印は日前神宮・國懸神宮の2社分を授与でき、御朱印コレクターにも好評。",
    "参拝情報": {
      "最寄り駅": "和歌山電鐵貴志川線「日前宮駅」より徒歩約2分。JR和歌山駅から和歌山電鐵で約3分。",
      "駐車場": "境内無料駐車場あり。",
      "授与所受付時間": "8:30〜16:30",
      "御朱印初穂料": "300円（各社）"
    },
    "公式URL": "https://hinokuma-jingu.com/",
    "参拝所要時間": "30〜45分（2社参拝を含む）",
    "ベストシーズン": {
      "春": "4月の参道の桜が美しい。",
      "夏": "夏の早朝参拝が清々しい。",
      "秋": "10月の秋季大祭。紀伊の秋空の下での参拝が格別。",
      "冬": "静寂の境内での新年参拝が好評。"
    },
    "セット参拝コース": [
      "和歌山1日3社コース：日前神宮・國懸神宮→伊太祁曽神社（電車15分）→和歌山城（電車5分）",
      "紀伊国3社コース：日前神宮・國懸神宮→伊太祁曽神社→丹生都比売神社（車で約40分）"
    ],
    "一人旅アクセス": {
      "電車のみで完結可": true,
      "駅から徒歩可": true,
      "最終アクセス難易度": "易",
      "女性一人歩き安全性コメント": "和歌山電鐵の日前宮駅から徒歩2分。住宅街の落ち着いた環境で安全。"
    }
  },
  {
    "id": "051",
    "name": "丹生都比売神社",
    "読み": "にうつひめじんじゃ",
    "旧国": "紀伊国",
    "都道府県": "和歌山県",
    "住所": "和歌山県伊都郡かつらぎ町上天野230",
    "緯度": 34.2231,
    "経度": 135.7264,
    "創建": "伝：今から1,700年以上前の創祀と伝えられる。創建年不詳だが、神功皇后の三韓征伐の折の説話が『播磨国風土記』に記載。史書上は平安時代の『続日本後紀』（承和6年・839年）に紀伊国一の宮として記録。2004年にユネスコ世界文化遺産「紀伊山地の霊場と参詣道」に登録。",
    "主祭神": "丹生都比売大神（にうつひめのおおかみ）",
    "配祀神": [
      "高野御子大神（たかのみこのおおかみ）",
      "大食津比売大神（おおけつひめのおおかみ）",
      "市杵島比売大神（いちきしまひめのおおかみ）"
    ],
    "ご利益": [
      "魔除け・厄払い",
      "縁結び",
      "病気平癒",
      "五穀豊穣",
      "学問成就",
      "世界遺産のパワー"
    ],
    "開運キーワード": "天照大御神の御妹神・丹（朱）の女神があらゆる災厄を祓う——高野山を空海に授けた女神の力",
    "開運フード": {
      "name": "柿の葉ずし・高野豆腐料理",
      "店または場所": "かつらぎ町周辺の飲食店・道の駅「くしがきの里」（かつらぎ町大字佐野702）。神社から車で約10分。",
      "効能": "柿の葉に含まれるビタミンCと殺菌効果が「魔除け」の食材とされ、紀伊山地の山岳信仰の食文化と結びつく。高野豆腐は高野山の修行食で精進料理の定番。",
      "エピソード": "丹生都比売神社は標高約450mの高野山麓・天野の里に鎮座する。「にほんの里100選」に選ばれた里山の風景と、慶長年間に淀殿が奉納したとされる朱色の輪橋（りんきょう）・鏡池は圧巻。世界遺産登録後は外国人参拝者も増加。（丹生都比売神社公式サイト・かつらぎ町観光協会参照）"
    },
    "必買お守り": [
      {
        "name": "魔除け守（まよけまもり）",
        "初穂料": "社務所にて（要現地確認）",
        "特徴": "丹生都比売大神は「丹（水銀朱）をつかさどる女神」であり、朱色は古来最強の魔除けの色。朱の女神に祈る魔除け守りは、丹生都比売神社ならではの授与品。",
        "どんな人向け": "邪気・厄災を払いたい人、新しいスタートを切る人"
      },
      {
        "name": "縁結守（えんむすびまもり）",
        "初穂料": "社務所にて（要現地確認）",
        "特徴": "丹生都比売大神は天照大御神の御妹神とも伝わり、縁結びの御神徳もある。世界遺産の神社で授かる縁結び守りとして人気。",
        "どんな人向け": "良縁・復縁を願う女性"
      },
      {
        "name": "世界遺産御守（せかいいさんおまもり）",
        "初穂料": "社務所にて（要現地確認）",
        "特徴": "ユネスコ世界文化遺産「紀伊山地の霊場と参詣道」の構成資産として登録されたことを記念したお守り。世界遺産の神社で授かる特別感がある。",
        "どんな人向け": "旅のお土産・特別な記念品を求める人"
      }
    ],
    "秘密の話": [
      {
        "title": "空海（弘法大師）に高野山を授けた女神——1200年前の神仏習合の出会い",
        "内容": "今から約1200年前、弘法大師空海が真言密教の根本道場の地を探していたとき、黒と白の2頭の犬を連れた猟師（高野御子大神の化身とされる）に導かれてこの地を訪れた。そこで丹生都比売大神が現れ、広大な山の土地を空海に譲ったのが現在の高野山とされる。丹生都比売神社は高野山の「地主神」であり、空海の真言密教が発展した土台を作った女神ともいわれる。",
        "ソース": "丹生都比売神社公式サイト「世界遺産について」（niutsuhime.or.jp）; 和歌山県公式観光サイト「空海を高野山へ導いた」記事"
      },
      {
        "title": "淀殿が奉納した「輪橋（りんきょう）」——慶長年間・朱塗りの反り橋",
        "内容": "境内入口の鏡池に架かる朱塗りの輪橋（反り橋）は、慶長年間（1596〜1615年）に豊臣秀吉の側室・淀殿が奉納したと伝わる。緩やかに弧を描く橋と鏡池の水面が織りなす光景は、全国的にも稀な美しさとして知られ、SNSで「日本最美の参道橋」として拡散されることも。",
        "ソース": "丹生都比売神社公式サイト（niutsuhime.or.jp）; かつらぎ町観光協会「丹生都比売神社」ページ"
      },
      {
        "title": "全国約180社の「丹生都比売神社」の総本社",
        "内容": "全国に約180社ある「丹生都比売神」を祀る神社の総本社がこの社。「丹生（にう）」は水銀朱の産地を意味し、古代に日本各地の水銀産地に丹生神社が建てられた歴史がある。紀伊半島は古代水銀の主要産地であり、この社がその総本社となった。丹（朱）は古代から呪術・医薬・建築（神社の朱色）に使われた神聖な物質。",
        "ソース": "丹生都比売神社公式サイト（niutsuhime.or.jp）; Wikipedia「丹生都比売神社」"
      }
    ],
    "女性人気ポイント": "朱塗りの輪橋と鏡池の美しさはSNS映え抜群で「和歌山で一番美しい神社」の呼び声が高い。世界遺産の神社という特別感。里山の静寂な雰囲気が「日常からの解放」を求める女性に響く。御朱印は通常版と季節限定版があり、コレクターにも人気。秋は紅葉と朱橋のコントラストが絶景。",
    "参拝情報": {
      "最寄り駅": "JR和歌山線「笠田駅」よりタクシーで約20分（バスは本数少ない）。車でのアクセスが便利（阪和道「かつらぎ西IC」より約20分）。",
      "駐車場": "神社前に無料駐車場あり（約50台）。",
      "授与所受付時間": "8:30〜16:30",
      "御朱印初穂料": "300円"
    },
    "公式URL": "https://niutsuhime.or.jp/",
    "参拝所要時間": "45〜60分",
    "ベストシーズン": {
      "春": "4〜5月の新緑と朱橋のコントラストが特に美しい。",
      "夏": "山麓の涼しい環境で夏でも参拝しやすい。",
      "秋": "11月の紅葉と鏡池の絶景。朱橋・紅葉・水面の三重奏が圧巻。",
      "冬": "雪景色の中の輪橋は幻想的。ただし山道の積雪・凍結に注意。"
    },
    "セット参拝コース": [
      "紀伊国3社コース：丹生都比売神社→（車60分）→伊太祁曽神社→日前神宮・國懸神宮",
      "高野山コース：丹生都比売神社→（車30分）→高野山（奥の院・金剛峯寺）"
    ],
    "一人旅アクセス": {
      "電車のみで完結可": false,
      "駅から徒歩可": false,
      "最終アクセス難易度": "難",
      "女性一人歩き安全性コメント": "山麓の山道のため車またはタクシー必須。レンタカーや高野山観光との組み合わせツアーが便利。バス便は本数が極めて少なく要事前確認。"
    }
  },
  {
    "id": "052",
    "name": "伊太祁曽神社",
    "読み": "いたきそじんじゃ",
    "旧国": "紀伊国",
    "都道府県": "和歌山県",
    "住所": "和歌山県和歌山市伊太祈曽558",
    "緯度": 34.2758,
    "経度": 135.238,
    "創建": "伝：垂仁天皇16年、日前神・国懸神が同所に祀られることになったため現在地近くの「亥の杜」に遷座。和銅6年（713年）に現在地に再遷座したことが『日本書紀』に関連記事あり。史書上は延長5年（927年）の『延喜式神名帳』に名神大社として記載。",
    "主祭神": "五十猛命（いたけるのみこと）別名：大屋毘古神（おおやびこのかみ）",
    "配祀神": [
      "大屋都比売命（おおやつひめのみこと）",
      "都麻津比売命（つまつひめのみこと）"
    ],
    "ご利益": [
      "木の守護・山林・木材業の守護",
      "厄除け",
      "病気平癒",
      "長寿",
      "縁結び",
      "農業守護"
    ],
    "開運キーワード": "日本の国土に木を植えた「緑の神」——木のぬくもりに触れながら命の根を張り直す",
    "開運フード": {
      "name": "いのちの水コーヒー（神水で淹れるスペシャルティコーヒー）",
      "店または場所": "伊太祁曽神社境内・社務所前の「神水カフェコーナー」。境内の霊泉「いのちの水」で淹れるスペシャルティコーヒーが提供される（季節・日程限定の場合あり）。",
      "効能": "神社の霊泉を使うことで神の恵みを体内に取り込む体験。「木の神」の境内で湧く水は命の源とされ、五十猛命の「命をはぐくむ」御神徳にちなむ。",
      "エピソード": "和歌山電鐵・貴志川線の「伊太祈曽駅」の隣に鎮座する独特のロケーション。和歌山電鐵は「たま電車」で有名な猫駅長ゆかりの路線。年に一度の「卯杖祭（うづえさい）」（1月）では小豆粥が振る舞われ、食べると1年間無病息災とされる由緒ある行事。（伊太祁曽神社公式サイト・和歌山道の駅ドットコム参照）"
    },
    "必買お守り": [
      {
        "name": "木の御守（きのおまもり）",
        "初穂料": "社務所にて（要現地確認）",
        "特徴": "五十猛命は日本書紀に「我が国に樹木を植えて廻った」と記される「木の神様」。木素材を使った独自の御守り。木のぬくもりを感じられる神社らしいお守り。伊太祁曽神社公式サイト記載。",
        "どんな人向け": "自然・木が好きな人、建築・木材業関係者、命の根を整えたい人"
      },
      {
        "name": "厄除守（やくよけまもり）",
        "初穂料": "社務所にて（要現地確認）",
        "特徴": "紀伊国一の宮として古来より厄除けの霊験あらたかとされる。特に「卯の年」「卯年生まれ」の人にゆかりある神社として知られる。",
        "どんな人向け": "厄年の人、健康祈願の参拝者"
      },
      {
        "name": "いのちの御守（いのちのおまもり）",
        "初穂料": "社務所にて（要現地確認）",
        "特徴": "五十猛命の「命をはぐくむ神」としての御神徳を宿す。長寿・健康・病気平癒を願うお守り。伊太祁曽神社公式サイト参照。",
        "どんな人向け": "健康長寿を願う人、家族の病気平癒を祈る人"
      }
    ],
    "秘密の話": [
      {
        "title": "もともと「日前宮」の場所にいた神——土地を明け渡した2700年の歴史",
        "内容": "伊太祁曽神社は創建当初、現在の日前神宮・國懸神宮（日前宮）の鎮座地に祀られていた。垂仁天皇16年に日前神・國懸神を同じ土地に祀ることになったため、五十猛命は自ら土地を明け渡して現在地に遷座した。「先住の神が後から来た神のために場所を譲った」という珍しい歴史を持ち、その謙虚さから「誠実な神」として信仰される。",
        "ソース": "伊太祁曽神社公式サイト由緒（itakiso-jinja.net）; Wikipedia「伊太祁曽神社」"
      },
      {
        "title": "『日本書紀』に記された「木の神」——日本の国土を緑で覆った神話",
        "内容": "五十猛命は『日本書紀』の「神代記」に、スサノオの子として朝鮮半島から日本へ渡り、日本全土に樹木の種を播いて国土を緑で覆ったと記される。これが日本の森林文化・木の文化の起源神話とされ、現在も全国の木材関係者・建築業者が参拝に訪れる。「きのくに（木の国）」という紀伊国の地名の由来ともいわれる。",
        "ソース": "伊太祁曽神社公式サイト（itakiso-jinja.net）; 『日本書紀』神代紀; 和歌山県観光公式サイト"
      },
      {
        "title": "和歌山電鐵「たま駅長」ゆかりの路線の駅と神社が隣接する珍しいロケーション",
        "内容": "伊太祁曽神社は和歌山電鐵・貴志川線の「伊太祈曽駅」のすぐ隣に鎮座している。この路線は世界的に有名になった「たま駅長（猫の駅長）」で知られ、2015年にたま駅長が神として祀られた「たま大明神」が貴志駅（終点）に創られた。一の宮参拝と「猫の路線」を組み合わせた「癒しの鉄道参拝旅」が女性に人気。",
        "ソース": "和歌山電鐵公式サイト（wakayama-dentetsu.co.jp）「伊太祁曽神社」ページ; 伊太祁曽神社公式サイト"
      }
    ],
    "女性人気ポイント": "「たま電車」で行く一の宮という珍しい体験が女性に大人気。境内の「なでしし」（猪の撫で物）や木のお守りがSNSでも話題。「木の神」の境内は緑豊かで心が落ち着く癒し系パワースポット。御朱印は月替わりのデザインがあり、コレクターに好評。",
    "参拝情報": {
      "最寄り駅": "和歌山電鐵貴志川線「伊太祈曽（いたきそ）駅」より徒歩約3分。JR和歌山駅から和歌山電鐵で約20分。",
      "駐車場": "神社前に無料駐車場あり。",
      "授与所受付時間": "9:00〜16:00",
      "御朱印初穂料": "300円（月替わりデザインあり）"
    },
    "公式URL": "https://www.itakiso-shrine.com/",
    "参拝所要時間": "30〜45分",
    "ベストシーズン": {
      "春": "3〜4月の桜の季節。たま電車の桜コースとしても人気。",
      "夏": "緑豊かな境内の木陰が涼しい。",
      "秋": "11月の紅葉。境内の古木が色づく。",
      "冬": "1月の「卯杖祭」は小豆粥の振る舞いがあり参拝者で賑わう。"
    },
    "セット参拝コース": [
      "和歌山電鐵1日コース：伊太祁曽神社→（電車10分）→日前神宮・國懸神宮→（電車3分）→和歌山城",
      "紀伊国3社コース：伊太祁曽神社→日前神宮・國懸神宮→丹生都比売神社（車）"
    ],
    "一人旅アクセス": {
      "電車のみで完結可": true,
      "駅から徒歩可": true,
      "最終アクセス難易度": "易",
      "女性一人歩き安全性コメント": "和歌山電鐵の駅隣接で非常にアクセスしやすい。路線自体が女性旅行者に人気の「たま電車」ルートで安心。"
    }
  },
  {
    "id": "053",
    "name": "出雲大神宮",
    "読み": "いずもだいじんぐう",
    "旧国": "丹波国",
    "都道府県": "京都府",
    "住所": "京都府亀岡市千歳町出雲無番地",
    "緯度": 35.016,
    "経度": 135.558,
    "創建": "伝：神代の昔に大国主命・三穂津姫命が鎮まったとされ、社殿の創建は和銅2年（709年）と伝わる。史書上は延長5年（927年）の『延喜式神名帳』に丹波国名神大社として記載。丹波国風土記逸文（「元明天皇和銅年中、大国主神の御一柱のみを島根の杵築に遷す」）にも言及あり。",
    "主祭神": "大国主命（おおくにぬしのみこと）",
    "配祀神": [
      "三穂津姫命（みほつひめのみこと）"
    ],
    "ご利益": [
      "縁結び（日本最強クラス）",
      "夫婦円満",
      "縁切り・悪縁断ち",
      "商売繁昌",
      "五穀豊穣",
      "家内安全"
    ],
    "開運キーワード": "「元出雲」——島根の出雲大社より古いとも伝わる縁結びの源流の地で本当の縁をつかむ",
    "開運フード": {
      "name": "亀岡牛のすき焼き・湯豆腐",
      "店または場所": "亀岡市内の飲食店（亀岡駅周辺）。「亀岡牛」は京都ブランド和牛で、神社参拝後の食事として地元に定着。湯豆腐は京都文化圏の精進料理の代表格。",
      "効能": "亀岡盆地の水と土地で育てられた地場食材。「縁結びの地」亀岡の風土のエネルギーを食で取り込む。",
      "エピソード": "出雲大神宮は「元出雲（もといずも）」「千年宮」とも称される。社伝では島根の出雲大社の方がこの社から分霊を受けたとされ、丹波国の「縁結びの本家」を主張する。本殿裏の磐座（いわくら）は古代の祭祀跡で、御影山（みかげやま）から湧き出る「真名井の水（まないのみず）」は霊水として人気。（出雲大神宮公式サイト・亀岡市観光協会参照）"
    },
    "必買お守り": [
      {
        "name": "縁結守（えんむすびまもり）・赤い糸のお守り",
        "初穂料": "社務所にて（要現地確認）",
        "特徴": "出雲大神宮の代表的な縁結び守り。境内の「夫婦岩」には参拝者が赤い糸を結ぶ慣わしがあり、そのお守りの赤い糸が縁結びを象徴する。「元出雲」の縁結び守りとして全国から女性が求めに来る。",
        "どんな人向け": "良縁・復縁を強く願う女性"
      },
      {
        "name": "夫婦守（めおとまもり）",
        "初穂料": "社務所にて（要現地確認）",
        "特徴": "大国主命と三穂津姫命の「夫婦神」が主祭神。夫婦円満・良縁成就の御神徳を宿す2個セットの守り。",
        "どんな人向け": "夫婦円満を願うカップル・夫婦"
      },
      {
        "name": "心願成就守（しんがんじょうじゅまもり）",
        "初穂料": "社務所にて（要現地確認）",
        "特徴": "大国主命は縁結びのみならず「農業・産業・国造りの神」として心願全般に効力があるとされる。",
        "どんな人向け": "大きな夢・目標に向けて動き出したい人"
      }
    ],
    "秘密の話": [
      {
        "title": "「元出雲」——島根の出雲大社より古いという社伝の謎",
        "内容": "出雲大神宮の社伝には、丹波国風土記逸文として「元明天皇の和銅年中（708〜715年）に大国主神の御一柱のみを島根の杵築に遷した」との記述が伝わる。つまり島根の出雲大社は、この丹波の「元出雲」から分祀されたと主張している。歴史的な真偽は研究者の間で議論があるが、「出雲大社より古い縁結びの聖地」という独自性が神社の大きな魅力となっている。",
        "ソース": "出雲大神宮公式サイト（izumo-d.org）由緒ページ; Wikipedia「出雲大神宮」; 京都旅屋「丹波国一の宮 出雲大神宮」"
      },
      {
        "title": "御影山から湧き出る霊水「真名井の水」——常に行列ができる神水",
        "内容": "境内の御神体山・御影山（みかげやま）から湧き出す「真名井の水（まないのみず）」は参拝者が自由に汲むことができ、「縁結びの神の霊水」として人気が高く、週末は行列ができることも。ペットボトル持参の参拝者が絶えない。",
        "ソース": "亀岡市観光協会「出雲大神宮」ページ（kameoka.info）; 京都ご利益.com「縁結びで有名な亀岡の出雲大神宮」"
      },
      {
        "title": "本殿裏の「磐座（いわくら）」——社殿建設以前の古代祭祀の跡",
        "内容": "本殿の真後ろに巨大な磐座（岩の祭祀場）が残されており、社殿が建てられるよりも古い時代から神が宿るとされてきた岩。一般参拝者が近づくことはできないが、本殿越しに磐座のエネルギーを感じる「背中のパワースポット」として参拝者に知られる。",
        "ソース": "京都ご利益.com「出雲大神宮」; フォートラベル「出雲大神宮クチコミ」"
      }
    ],
    "女性人気ポイント": "「元出雲」の縁結びという独自ブランドが口コミで女性に大人気。夫婦岩への赤い糸結びはカップル・女友達参拝の定番体験。真名井の水汲みは「神様の水を持ち帰る特別感」が高い。境内の紅葉（11月）は京都府内でも有数の美しさとして知られる。",
    "参拝情報": {
      "最寄り駅": "JR嵯峨野線「亀岡駅」から亀岡市ふるさとバス「出雲大神宮前」下車。または「千歳車庫前」下車徒歩15分。大阪・京都から約30〜40分。",
      "駐車場": "神社前に無料駐車場あり（約30台）。",
      "授与所受付時間": "9:00〜16:00",
      "御朱印初穂料": "300円"
    },
    "公式URL": "http://izumo-d.org/",
    "参拝所要時間": "40〜60分",
    "ベストシーズン": {
      "春": "4月の桜と新緑。嵯峨野・保津峡と組み合わせた春の京都旅が人気。",
      "夏": "7月の七夕祈願が女性に人気。",
      "秋": "11月の紅葉が圧巻。紅葉と磐座の組み合わせが神秘的。",
      "冬": "静寂の境内での縁結び参拝。年末年始の参拝者増。"
    },
    "セット参拝コース": [
      "丹波・丹後コース：出雲大神宮（亀岡）→（電車2時間）→籠神社（天橋立）",
      "亀岡1日コース：出雲大神宮→保津川下り→嵯峨野トロッコ列車"
    ],
    "一人旅アクセス": {
      "電車のみで完結可": true,
      "駅から徒歩可": false,
      "最終アクセス難易度": "中",
      "女性一人歩き安全性コメント": "亀岡駅からバスでアクセス可能。バスの本数が少ないため時刻表の事前確認が必要。タクシーも利用可（駅から約10分・約1,500円）。"
    }
  },
  {
    "id": "054",
    "name": "籠神社",
    "読み": "このじんじゃ",
    "旧国": "丹後国",
    "都道府県": "京都府",
    "住所": "京都府宮津市大垣430",
    "緯度": 35.5792,
    "経度": 135.1887,
    "創建": "伝：神代の昔に彦火明命が天降った地として記録。社殿の創建年は不詳だが、平安時代の延長5年（927年）の『延喜式神名帳』に丹後国名神大社・山陰道唯一の最高格式として記載。天橋立に隣接する「元伊勢」として古来より崇敬される。",
    "主祭神": "彦火明命（ひこほあかりのみこと）",
    "配祀神": [
      "豊受大神（とようけのおおかみ）",
      "天照大神（あまてらすおおかみ）",
      "海神（わたつみ）",
      "天水分神（あめのみくまりのかみ）"
    ],
    "ご利益": [
      "縁結び",
      "航海安全",
      "漁業守護",
      "豊穣",
      "家内安全",
      "学業成就",
      "伊勢神宮に準ずる格式の祈願全般"
    ],
    "開運キーワード": "伊勢神宮の「ふるさと」——天照大神と豊受大神が鎮まっていた聖地で、すべての願いの源流に触れる",
    "開運フード": {
      "name": "天橋立ビューランドのソフトクリーム・かに料理（宮津の名物）",
      "店または場所": "天橋立食堂・宮津市内の民宿・料理店。籠神社から天橋立を渡った先に飲食店多数。宮津かにが特に有名（冬季・松葉ガニ解禁後）。",
      "効能": "丹後・宮津は日本三景のひとつ「天橋立」で知られ、海の恵みを食する「海神への感謝の食」として地元で親しまれる。",
      "エピソード": "籠神社は天橋立の北端に位置し、奥宮「真名井神社（まないじんじゃ）」は徒歩約15分の場所にある。真名井神社の本殿裏には古代の磐座（いわくら）が現存し、「磐座を背後から感じる参拝」は特別体験として知られる。本殿は伊勢神宮と同じ神明造。（籠神社公式サイト・丹後観光ガイド参照）"
    },
    "必買お守り": [
      {
        "name": "月みくじ",
        "初穂料": "社務所にて（要現地確認）",
        "特徴": "月の満ち欠けをテーマにした言葉が添えられた独自デザインのおみくじ。引いた後に何度も読み返したくなる内容と美しいデザインで、女性の口コミで人気に。籠神社公式サイト記載。",
        "どんな人向け": "日々の指針・言葉の力を求める女性"
      },
      {
        "name": "縁結守（えんむすびまもり）",
        "初穂料": "社務所にて（要現地確認）",
        "特徴": "丹後国一の宮・元伊勢の縁結び守り。天照大神と豊受大神が鎮まった「元伊勢」ならではの格式を持つ。",
        "どんな人向け": "良縁・縁強化を願う女性全般"
      },
      {
        "name": "海神守（わたつみまもり）",
        "初穂料": "社務所にて（要現地確認）",
        "特徴": "籠神社の海神（わたつみ）の御神徳を宿す航海・旅行安全の守り。日本海を望む地ならではのお守り。",
        "どんな人向け": "旅好きの女性・船・水に関わる仕事の人"
      }
    ],
    "秘密の話": [
      {
        "title": "伊勢神宮の「元の鎮座地」——天照大神と豊受大神が伊勢に移る前にいた場所",
        "内容": "籠神社は「元伊勢（もといせ）」の称号を持つ。天照大神が垂仁天皇25年に伊勢の現在地に遷る前、豊受大神が雄略天皇22年に伊勢に遷る前、それぞれがこの丹後の地（籠神社の地）に鎮まっていたとされる。つまり三重の伊勢神宮はここから分かれた——という信仰が成立し、「元伊勢籠神社」の正式名称になっている。",
        "ソース": "籠神社公式サイト（motoise.jp）「御祭神・御由緒」ページ; 宮津市公式サイト「元伊勢籠神社」"
      },
      {
        "title": "伊勢神宮と2か所にしか存在しない「五色の座玉」",
        "内容": "籠神社の本殿・高欄の上には青・黄・赤・白・黒の「五色の座玉（すえだま）」が並んでいる。この座玉は伊勢神宮の御正殿と籠神社の2か所にしか存在しない特別な意匠で、籠神社が伊勢神宮と同等の格式を持つことの証とされる。",
        "ソース": "籠神社公式サイト（motoise.jp）; 宮津市公式サイト「五色の座玉」解説; 奥宮・真名井神社紹介ページ"
      },
      {
        "title": "社家・海部氏の系図は「国宝」——1400年を超える日本最古級の家系記録",
        "内容": "籠神社の宮司家・海部氏（あまべし）が伝える「海部氏系図」は国宝に指定されており、9世紀（平安時代初期）に記された日本最古級の家系図のひとつ。1400年以上にわたって同じ家系が神社を守り続けてきたことを証明する文書で、日本の神社史上でも極めて稀な存在。",
        "ソース": "籠神社公式サイト（motoise.jp）「御由緒・文化財」; 宮津市公式観光サイト"
      }
    ],
    "女性人気ポイント": "日本三景・天橋立との組み合わせ観光が定番で、一の宮参拝と絶景旅を同時に楽しめる。奥宮・真名井神社の磐座は「パワースポット女子旅」の定番スポット。月みくじのデザインがSNS映えすると話題。伊勢神宮の「ルーツ」に触れる体験は特別感が高い。御朱印は通常・奥宮（真名井神社）の2か所。",
    "参拝情報": {
      "最寄り駅": "京都丹後鉄道「天橋立駅」から徒歩約15分、またはバス・タクシーで約5分。京都・大阪から特急「はしだて」で約2時間。",
      "駐車場": "神社前に有料駐車場あり（200円程度）。",
      "授与所受付時間": "8:00〜17:00",
      "御朱印初穂料": "300円（籠神社・奥宮真名井神社それぞれ）"
    },
    "公式URL": "https://www.motoise.jp/",
    "参拝所要時間": "60〜90分（奥宮・真名井神社を含む）。天橋立観光を加えると半日。",
    "ベストシーズン": {
      "春": "4〜5月の天橋立の松並木の新緑が美しい。",
      "夏": "7〜8月の海水浴・天橋立川床と組み合わせた夏の丹後旅。",
      "秋": "10〜11月の紅葉と日本海の青さのコントラスト。松葉ガニ解禁（11月〜）も見逃せない。",
      "冬": "松葉ガニの季節（11〜3月）。冬の日本海の荒々しさと神社の荘厳さが格別。"
    },
    "セット参拝コース": [
      "丹後一の宮コース：籠神社→奥宮真名井神社→天橋立展望（傘松公園）",
      "丹波・丹後2社コース：籠神社（天橋立）→（電車2時間）→出雲大神宮（亀岡）"
    ],
    "一人旅アクセス": {
      "電車のみで完結可": true,
      "駅から徒歩可": true,
      "最終アクセス難易度": "中",
      "女性一人歩き安全性コメント": "天橋立駅から歩ける距離だが、天橋立の松並木を歩く場合は砂利道のため歩きやすい靴推奨。観光地として整備されており安全。"
    }
  },
  {
    "id": "055",
    "name": "粟鹿神社",
    "読み": "あわがじんじゃ",
    "旧国": "但馬国",
    "都道府県": "兵庫県",
    "住所": "兵庫県朝来市山東町粟鹿2152",
    "緯度": 35.278,
    "経度": 134.8625,
    "創建": "伝：垂仁天皇の御代（1〜70年頃）以前から鎮座し、2,000年以上の歴史を持つと伝えられる。史書上は延長5年（927年）の『延喜式神名帳』に但馬国名神大社として記載。神功皇后の三韓征伐の際に神助があったと伝わる。",
    "主祭神": "彦火火出見命（ひこほほでみのみこと）",
    "配祀神": [
      "龍神（りゅうじん）",
      "豊玉姫命（とよたまひめのみこと）"
    ],
    "ご利益": [
      "縁結び・良縁",
      "安産",
      "農業・五穀豊穣",
      "海上安全",
      "家内安全",
      "長寿"
    ],
    "開運キーワード": "「竹田城跡の見える但馬の古社」——山と谷の霊気が溜まる2000年の聖地で縁と豊穣を祈る",
    "開運フード": {
      "name": "但馬牛料理（朝来・和田山周辺）",
      "店または場所": "朝来市内・和田山周辺の但馬牛専門店。「山陰近畿自動車道山東IC」近くに飲食店複数あり。",
      "効能": "但馬牛は神戸牛・松阪牛などブランド和牛の祖先。「神の恵みの肉」として古来より但馬の土地で育まれた。",
      "エピソード": "粟鹿神社は「天空の城」で有名な竹田城跡（車で約15分）と同エリアにある。竹田城跡との組み合わせ観光が人気で、朝霧の時期（秋〜冬朝）に雲海を見てから参拝するルートが女性旅行者に定番化している。山東盆地の自然の中に鎮まる杜は、都会と正反対の静寂と霊気を持つ。（朝来市観光協会・まるごと北近畿参照）"
    },
    "必買お守り": [
      {
        "name": "縁結守（えんむすびまもり）",
        "初穂料": "書置き御朱印300円ほか授与品あり（社務所にて確認）",
        "特徴": "彦火火出見命（海幸彦・山幸彦神話の山幸彦）と豊玉姫命の夫婦神が主祭神。縁結び・夫婦円満の御神徳が強い。",
        "どんな人向け": "良縁・夫婦円満を願う人"
      },
      {
        "name": "安産守（やすみまもり）",
        "初穂料": "社務所にて（要現地確認）",
        "特徴": "豊玉姫命は海神の娘で、海の中の産屋で子を産んだ神話から「安産の神」として信仰される。",
        "どんな人向け": "妊婦・子授けを願う女性"
      },
      {
        "name": "長寿守（ちょうじゅまもり）",
        "初穂料": "社務所にて（要現地確認）",
        "特徴": "彦火火出見命は長寿の神としての信仰も持ち、高齢者からも参拝される。長寿・健康の御守り。",
        "どんな人向け": "長寿・健康を願う人、高齢の親へのお土産"
      }
    ],
    "秘密の話": [
      {
        "title": "「アワ（粟）をくわえた鹿」が神の使いとなった神社名の由来",
        "内容": "彦火火出見命が国見山に登った際、粟の穂をくわえた鹿が命のもとにやってきたという伝承がある。この「粟（アワ）をくわえた鹿（シカ）」が神の使いとして認められ、「粟鹿（アワガ）神社」の名が生まれた。粟は古代の主要穀物であり、五穀豊穣を象徴する神社名として但馬の農耕文化と深く結びついている。",
        "ソース": "粟鹿神社（全国一宮巡礼サイト）由緒; 朝来市観光協会「粟鹿神社」ページ"
      },
      {
        "title": "神功皇后の三韓征伐を神助した「但馬の守護神」",
        "内容": "神功皇后が三韓征伐（朝鮮半島遠征）に臨んだ際、粟鹿神社の神が神助を授け、凱旋後に奉幣使を立てたという伝説が残る。但馬国の精神的支柱として古代から機能しており、歴代の朝廷・武将からも崇敬を受けてきた。",
        "ソース": "兵庫県立歴史博物館「名所めぐり：粟鹿神社」（rekihaku.pref.hyogo.lg.jp）; 粟鹿神社Wikipedia"
      },
      {
        "title": "竹田城跡と但馬の霊気——「天空の城」と2000年の杜が生み出すエネルギーライン",
        "内容": "粟鹿神社がある朝来盆地は、「日本のマチュピチュ」と呼ばれる竹田城跡（標高353m）を擁する霊気の濃い土地とされる。竹田城跡の雲海は旧暦の秋〜冬の早朝にのみ発生する神秘的な景観で、雲海を見てから麓の粟鹿神社で参拝するという「霊気コース」が女性旅行者の間で口コミで広まっている。",
        "ソース": "朝来市観光協会「竹田城跡と粟鹿神社」; まるごと北近畿「粟鹿神社」ページ"
      }
    ],
    "女性人気ポイント": "竹田城跡との組み合わせで「天空の城と2000年の杜」を1日で体験できる特別感。山間の静寂な杜は都会の疲れを癒すパワースポットとして口コミで広がっている。御朱印は書置きで授与（社務所前の玄関先）。但馬牛・黒豆・丹波栗など地場グルメも豊富。",
    "参拝情報": {
      "最寄り駅": "JR山陰本線「梁瀬（やなせ）駅」からタクシーで約10分（電車のみでの徒歩アクセスは困難）。車：北近畿豊岡自動車道「山東IC」から約10分。",
      "駐車場": "境内入口に無料駐車場あり。",
      "授与所受付時間": "社務所（不定期）。御朱印は鳥居前の書置きボックスから（300円・料金箱投入式）。",
      "御朱印初穂料": "300円（書置き）"
    },
    "公式URL": "https://kitakinki.gr.jp/spot/656（まるごと北近畿ページ）",
    "参拝所要時間": "20〜30分",
    "ベストシーズン": {
      "春": "4〜5月の新緑と竹田城跡の桜との組み合わせ。",
      "夏": "緑深い杜での夏の参拝が清涼。",
      "秋": "10〜11月の竹田城跡雲海シーズンと連動した参拝が人気。紅葉も美しい。",
      "冬": "竹田城跡の雲海は11月末〜2月が最もよく発生。早朝雲海→午前中粟鹿神社参拝のコース。"
    },
    "セット参拝コース": [
      "但馬2社コース：粟鹿神社→（車30分）→出石神社（出石町）",
      "天空の城コース：竹田城跡（早朝雲海）→粟鹿神社→和田山の但馬牛グルメ"
    ],
    "一人旅アクセス": {
      "電車のみで完結可": false,
      "駅から徒歩可": false,
      "最終アクセス難易度": "難",
      "女性一人歩き安全性コメント": "公共交通機関のみでの訪問は難しい。レンタカーまたはタクシー必須。竹田城跡観光とのセットでレンタカーを借りるプランが最も効率的。"
    }
  },
  {
    "id": "056",
    "name": "出石神社",
    "読み": "いずしじんじゃ",
    "旧国": "但馬国",
    "都道府県": "兵庫県",
    "住所": "兵庫県豊岡市出石町宮内99",
    "緯度": 35.4705,
    "経度": 134.8768,
    "創建": "伝：垂仁天皇3年、新羅の王子・天日槍命（あめのひぼこのみこと）が新羅から持ち込んだ八種の神宝を出石の地に祀ったのが起源とされる。史書上は『古事記』・『日本書紀』に天日槍命の渡来記事あり（垂仁天皇紀）。延長5年（927年）の延喜式に名神大社として記載。",
    "主祭神": "伊豆志八前大神（いずしやまえのおおかみ）—天日槍命が持ち込んだ8種の神宝を神格化したもの",
    "配祀神": [
      "天日槍命（あめのひぼこのみこと）"
    ],
    "ご利益": [
      "縁結び・良縁",
      "安産",
      "商売繁昌",
      "武運・勝負運",
      "旅行安全",
      "異文化との縁"
    ],
    "開運キーワード": "朝鮮半島から渡来した「異国の王子の神」——海を越えた縁と勇気の神から、新しい世界への一歩を授けてもらう",
    "開運フード": {
      "name": "出石皿そば（いずしさらそば）",
      "店または場所": "出石城下町・本町・宗鏡寺参道周辺の出石そば店多数。「近又（ちかまた）」「但馬屋」「伊豆味（いずみ）」など50軒以上の専門店が城下町に集積。",
      "効能": "出石そばは約320年前、信州（長野）から出石藩に招かれたそば職人が持ち込んだ技術が発展したもの。5枚の小皿に盛られた「皿そば」を食べ、食べた枚数で運勢を占う遊びも有名。",
      "エピソード": "出石町は「但馬の小京都」と称される江戸時代の城下町の街並みが今も残る観光地。出石城跡・辰鼓楼（時計台）・そば屋が立ち並ぶ石畳の通りは女性旅行者に大人気。出石神社と城下町観光の組み合わせは兵庫北部を代表する旅コース。（出石観光協会公式サイト参照）"
    },
    "必買お守り": [
      {
        "name": "縁結守（えんむすびまもり）",
        "初穂料": "社務所にて（要現地確認）",
        "特徴": "天日槍命は妻を追って日本に渡来したという神話を持ち、「妻への愛を追い求めた神」として縁結び・復縁の御神徳がある。出石神社独自の縁結び守り。",
        "どんな人向け": "良縁・復縁を強く願う女性"
      },
      {
        "name": "旅行安全守（たびあんぜんまもり）",
        "初穂料": "社務所にて（要現地確認）",
        "特徴": "天日槍命は海を渡って新羅から日本に来た「旅の神」。旅行・出張・海外渡航の安全を守るお守り。",
        "どんな人向け": "旅好き女性・出張族・海外在住者"
      },
      {
        "name": "勝運守（しょううんまもり）",
        "初穂料": "社務所にて（要現地確認）",
        "特徴": "天日槍命は武勇に優れた王子として伝わり、勝負運・仕事での勝利を願う参拝者が多い。",
        "どんな人向け": "仕事・受験・スポーツで勝負に臨む人"
      }
    ],
    "秘密の話": [
      {
        "title": "妻を追って海を渡った新羅の王子——古事記・日本書紀に登場する渡来神",
        "内容": "天日槍命は『古事記』・『日本書紀』に「新羅の王子として日本に渡来した」と記される珍しい「外国出身の神」。新羅で美しい女性（阿加流比売・あかるひめ）を妻にしていたが、妻が日本に逃れてしまい、妻を追って新羅の神宝8種を携えて渡日したとされる。「妻への愛のために海を越えた神」として縁結び信仰の根拠となっている。",
        "ソース": "出石神社由緒（daytrip-izushi.jp）; 豊岡市観光公式サイト（toyooka-tourism.com）; 『古事記』垂仁天皇段; Wikipedia「出石神社」"
      },
      {
        "title": "『古事記』・『日本書紀』両方に登場する——1,300年以上記録された歴史",
        "内容": "出石神社の御祭神・天日槍命は、現存する日本最古の歴史書『古事記』（712年）と『日本書紀』（720年）の両方に登場する。神話の時代から文字で記録された「渡来系の神」は日本の神社史上でも極めて稀であり、古代の日朝文化交流の証拠としても歴史的価値が高い。",
        "ソース": "豊岡市観光公式サイト「出石神社・但馬の開祖」（toyooka-tourism.com）; 『古事記』; Wikipedia「天日槍」"
      },
      {
        "title": "城下町「但馬の小京都・出石」のランドマーク——城跡・時計台・そば屋と共存する一の宮",
        "内容": "出石町は江戸時代・出石藩（5万8千石）の城下町としての街並みが今も残り、出石城跡・国内最古の時計台「辰鼓楼」・50軒以上の皿そば屋が石畳の通りに並ぶ。その城下町の北側に出石神社が鎮座する独特のロケーション。神社と城下町が一体となった観光地は全国的にも珍しく、女性の日帰り旅行に最適。",
        "ソース": "出石観光協会公式サイト（izushi.co.jp）; 豊岡市観光公式サイト"
      }
    ],
    "女性人気ポイント": "出石の城下町観光（皿そば・街並み散歩）と神社参拝が1日で完結する最高のセット旅行。「妻を追って海を越えた神」という神話のロマンが女性の心を掴む。皿そばの枚数占いはSNS映えする楽しい体験。御朱印は直書き対応。",
    "参拝情報": {
      "最寄り駅": "JR山陰本線「江原駅」から全但バスで約30分「出石」下車。または豊岡駅からバスで約40分。車：北近畿豊岡道「出石IC」から約5分。",
      "駐車場": "神社前に無料駐車場あり。城下町中心部の町営駐車場も利用可（300円）。",
      "授与所受付時間": "9:00〜16:00（社務所）",
      "御朱印初穂料": "300円"
    },
    "公式URL": "https://toyooka-tourism.com/spot/izushijinja/",
    "参拝所要時間": "30〜45分",
    "ベストシーズン": {
      "春": "4〜5月の出石城跡の桜と石畳の街並みが美しい。",
      "夏": "夏の城下町散歩と皿そばが爽快。",
      "秋": "10〜11月の紅葉。但馬の秋景色が格別。",
      "冬": "松葉ガニの季節（11〜3月）に合わせた但馬旅の拠点として人気。"
    },
    "セット参拝コース": [
      "但馬2社コース：出石神社→（車30分）→粟鹿神社",
      "出石1日観光：出石神社→出石城跡→皿そば食べ歩き（城下町）→辰鼓楼"
    ],
    "一人旅アクセス": {
      "電車のみで完結可": false,
      "駅から徒歩可": false,
      "最終アクセス難易度": "中",
      "女性一人歩き安全性コメント": "バスで「出石」バス停まで来れば城下町と神社は徒歩圏内。城下町自体が観光地として整備されており安全。バスの時刻表を事前確認すること。"
    }
  },
  {
    "id": "057",
    "name": "伊和神社",
    "読み": "いわじんじゃ",
    "旧国": "播磨国",
    "都道府県": "兵庫県",
    "住所": "兵庫県宍粟市一宮町須行名407",
    "緯度": 35.0838,
    "経度": 134.5025,
    "創建": "伝：成務天皇14年（144年）または欽明天皇25年（564年）の創祀と伝わる。史書上は延長5年（927年）の延喜式神名帳に播磨国名神大社として記載。欽明天皇25年、豪族・伊和恒郷への大己貴神の神託によって一夜にして木々が群生し、白鶴2羽が石の上で北向きに眠っていたとの伝承がある。",
    "主祭神": "大己貴神（おおなむちのかみ）別名：大国主命（おおくにぬしのみこと）",
    "配祀神": [],
    "ご利益": [
      "縁結び",
      "農業・産業守護",
      "病気平癒",
      "縁切り（悪縁断ち）",
      "交通安全",
      "心願成就"
    ],
    "開運キーワード": "播磨国の大地を作った神——1800年の杜に宿るシシ神の気配の中で、ゆっくり心を整える",
    "開運フード": {
      "name": "宍粟の地酒・播州百日どり（地鶏料理）",
      "店または場所": "宍粟市内の飲食店・道の駅「播磨いちのみや」（宍粟市一宮町東上野34-2）。神社から徒歩5分。",
      "効能": "宍粟（しそう）は中国山地の清流に育まれた山と水の町。日本酒の産地・播州の地酒は神前にも供えられる縁起物。",
      "エピソード": "伊和神社は兵庫県の山奥・宍粟市（しそうし）に鎮座し、播磨国一の宮として格式が高い。境内の「鶴石（つるいし）」は御祭神が顕現した伝説の石で、今も境内に祀られている。社殿は北向きという全国的にも珍しい向きで、これは鶴が北向きに眠っていた伝承に由来する。（兵庫県観光サイト・宍粟ツーリズムガイド参照）"
    },
    "必買お守り": [
      {
        "name": "縁結守（えんむすびまもり）",
        "初穂料": "社務所にて（要現地確認）",
        "特徴": "大己貴神（大国主命）は縁結びの神の代表格。出雲大社の主祭神と同一神であり、播磨国での縁結びの御神徳は格別。",
        "どんな人向け": "良縁を強く願う女性"
      },
      {
        "name": "病気平癒守（びょうきへいゆまもり）",
        "初穂料": "社務所にて（要現地確認）",
        "特徴": "大己貴神は医薬・病気平癒の神としても信仰される。少彦名命とともに医療の神として古事記に記されており、病気平癒の祈願者が多い。",
        "どんな人向け": "病気療養中の人、家族の健康回復を願う人"
      },
      {
        "name": "交通安全守（こうつうあんぜんまもり）",
        "初穂料": "社務所にて（要現地確認）",
        "特徴": "播磨国の守護神として、国道29号線（宍粟市の主要道路）を利用するドライバーが交通安全を祈願して参拝する慣わしが続く。",
        "どんな人向け": "車・バイク通勤の人、遠距離ドライブを控えた人"
      }
    ],
    "秘密の話": [
      {
        "title": "北向きの本殿——白鶴が北向きに眠っていた伝承で社殿の向きが決まった",
        "内容": "全国的に神社の本殿は南向きが一般的だが、伊和神社の本殿は北向きという珍しい形態。欽明天皇25年、豪族・伊和恒郷に大己貴神から「我を祀れ」との神託があり、西の野に一夜にして木々が生い茂り、白鶴2羽が石（鶴石）の上で北向きに眠っているのを発見。その場所に北向きのまま社殿を建てたとされる。「鶴石」は今も境内に現存する。",
        "ソース": "伊和神社Wikipedia; 宍粟ツーリズムガイド（shiso.or.jp）; 兵庫県観光サイト（hyogo-tourism.jp）"
      },
      {
        "title": "播磨国を作った大己貴神——播磨国風土記に最も多く登場する神",
        "内容": "『播磨国風土記』（713年頃）は現存する最古の地方風土記のひとつで、大己貴神（大国主命）が播磨国の各地を巡って地名の由来を作ったという記事が数多く収録されている。伊和神社の祭神は播磨の国土を形成した神として、播磨全域の守護神的存在。",
        "ソース": "伊和神社Wikipedia; 兵庫県立歴史博物館「播磨国風土記」資料"
      },
      {
        "title": "宍粟市という山奥の秘境に鎮座する「穴場の一の宮」",
        "内容": "伊和神社は兵庫県北西部・中国山地の山間にある宍粟市（しそうし）に鎮座し、全国の一の宮の中でもアクセスが不便な「秘境型一の宮」として知られる。それゆえ参拝者数は少なめで静寂な境内が保たれており、「人が少なくて神気が濃い一の宮」として御朱印巡りの愛好者の間で密かに人気が高まっている。",
        "ソース": "フォートラベル「播磨国一宮伊和神社クチコミ」; 全国一宮巡拝会ページ"
      }
    ],
    "女性人気ポイント": "人混みを避けた静寂な一の宮として御朱印愛好者の「穴場」として口コミ人気が急上昇。北向きの本殿・鶴石という全国的に珍しい見どころがある。道の駅「播磨いちのみや」が隣接しており、参拝後の休憩・グルメが便利。御朱印は社務所にて直書き対応。",
    "参拝情報": {
      "最寄り駅": "JR姫路駅から神姫バス（播但交通）「一宮（いちのみや）」バス停下車徒歩約3分（約1時間20分）。車：中国道「山崎IC」から約10分が便利。",
      "駐車場": "境内前に無料駐車場あり。",
      "授与所受付時間": "9:00〜16:00（社務所）",
      "御朱印初穂料": "300円"
    },
    "公式URL": "https://www.hyogo-tourism.jp/spot/detail_1042.html（兵庫県観光サイト）",
    "参拝所要時間": "30〜45分",
    "ベストシーズン": {
      "春": "4〜5月の新緑と清流・揖保川（いぼがわ）の景観が美しい。",
      "夏": "宍粟の山の空気が清涼で避暑地的な雰囲気。",
      "秋": "10〜11月の紅葉が境内を彩る。周辺の宍粟50名山のハイキングとの組み合わせも人気。",
      "冬": "静寂な雪景色の境内。山間部のため積雪・凍結に要注意。"
    },
    "セット参拝コース": [
      "播磨・但馬コース：伊和神社→（車1.5時間）→出石神社（但馬）",
      "姫路1日コース：伊和神社（午前）→姫路城・書寫山圓教寺（午後）"
    ],
    "一人旅アクセス": {
      "電車のみで完結可": false,
      "駅から徒歩可": false,
      "最終アクセス難易度": "難",
      "女性一人歩き安全性コメント": "バスでのアクセスも可能だが本数が少なく事前確認必須。道の駅が隣接しており、日中は安全。車（レンタカー）での訪問が最も快適。"
    }
  },
  {
    "id": "058",
    "name": "伊弉諾神宮",
    "読み": "いざなぎじんぐう",
    "旧国": "淡路国",
    "都道府県": "兵庫県",
    "住所": "兵庫県淡路市多賀740",
    "緯度": 34.4448,
    "経度": 134.901,
    "創建": "伝：神代の昔に国産み・神産みを終えた伊弉諾尊が最初に生んだ淡路島・多賀の地の「幽宮（かくりのみや）」に鎮まったのが起源。史書上は『古事記』・『日本書紀』に伊弉諾尊の終焉の地として淡路島が明記されており、日本神話に登場する最古の神社のひとつ。現在の社殿は明治時代に整備。",
    "主祭神": "伊弉諾大神（いざなぎのおおかみ）・伊弉冉大神（いざなみのおおかみ）",
    "配祀神": [],
    "ご利益": [
      "縁結び・夫婦円満（最強クラス）",
      "安産・子授け",
      "厄除け",
      "国産み（創造）のパワー",
      "長寿",
      "縁起全般"
    ],
    "開運キーワード": "日本の国を生んだ夫婦神の「終の住処」——最初の夫婦神に、現代の縁と創造の力を授けてもらう",
    "開運フード": {
      "name": "淡路島たまねぎ料理・淡路島牛丼",
      "店または場所": "淡路市内・淡路SA（高速道路上り・下り）・淡路島各所の飲食店。「道の駅あわじ」（淡路市岩屋925-119）でたまねぎ丼・たまねぎスープなど。神社から車で約20分。",
      "効能": "淡路島産たまねぎは日本一の生産量を誇り、「淡路の玉ねぎは縁起物」として地元で語られる。玉ねぎの丸い形は縁結び・縁（円）の象徴ともされる。",
      "エピソード": "伊弉諾神宮は「日本最古の神社」とも称され、境内には樹齢約900年・兵庫県指定天然記念物の「夫婦大楠（めおとおおくす）」がある。2本の楠が根元で結合した御神木は夫婦円満・縁結びの象徴として参拝者が抱きつく慣わしがある。（伊弉諾神宮公式サイト・淡路島観光ガイド参照）"
    },
    "必買お守り": [
      {
        "name": "縁結守（えんむすびまもり）",
        "初穂料": "社務所にて（要現地確認）",
        "特徴": "伊弉諾・伊弉冉の「最初の夫婦神」が主祭神。日本で最初の縁結びの神として「縁結び守りの原点」的存在。",
        "どんな人向け": "縁結びを願うすべての女性"
      },
      {
        "name": "夫婦楠守（めおとくすまもり）",
        "初穂料": "社務所にて（要現地確認）",
        "特徴": "境内の夫婦大楠（樹齢約900年）にちなんだ夫婦円満・家内安全の御守り。御神木の霊力を宿すとされる。",
        "どんな人向け": "夫婦円満・良縁継続を願うカップル・夫婦"
      },
      {
        "name": "安産守（あんざんまもり）",
        "初穂料": "社務所にて（要現地確認）",
        "特徴": "伊弉諾・伊弉冉の2神は日本の神々すべてを産んだ「産みの神」。安産・子授けの御神徳は日本最高クラスとされる。",
        "どんな人向け": "妊婦・子授けを強く願う女性"
      }
    ],
    "秘密の話": [
      {
        "title": "日本最初の夫婦神が「最初に生んだ島・淡路島」に眠る——『古事記』・『日本書紀』の聖地",
        "内容": "『古事記』・『日本書紀』の「国産み神話」では、伊弉諾・伊弉冉の2神がまず最初に淡路島を生み、その後本州・四国・九州などを生んだとされる。国産みを終えた伊弉諾尊は最後に淡路島の多賀の地に「幽宮（かくりのみや・隠れ住む宮殿）」を建てて鎮まった。日本神話に明記された「神様の終の住処」に建てられた神宮は、他に類を見ない特別な聖地。",
        "ソース": "伊弉諾神宮公式サイト（kuniuminoshima.jp）; 『古事記』; 『日本書紀』神代紀"
      },
      {
        "title": "夫婦大楠——2本の楠が根元で結合した樹齢900年の御神木",
        "内容": "境内に鎮まる「夫婦大楠」は、2本の楠の木が根元で一体化した珍しい御神木で、樹齢約900年。兵庫県指定天然記念物。伊弉諾・伊弉冉の夫婦神の象徴として、縁結び・夫婦円満・安産のパワースポットとして参拝者が幹に触れる慣わしがある。",
        "ソース": "伊弉諾神宮公式サイト（kuniuminoshima.jp）; 淡路島観光ガイド（awajishima-kanko.jp）"
      },
      {
        "title": "「日本最古の神社」の称号と、伊勢神宮との深い関係",
        "内容": "伊弉諾神宮は『古事記』・『日本書紀』に根拠を持つ点で「日本最古の神社のひとつ」として知られる。また、伊弉諾尊は伊勢神宮の主祭神・天照大神の父神であり、伊弉諾神宮は「天照大神の父の終焉の地」でもある。伊勢神宮が「天照大神を祀る社」なら、伊弉諾神宮は「天照大神の父母の社」という関係性が成り立つ。",
        "ソース": "伊弉諾神宮公式サイト（kuniuminoshima.jp）由緒; 国學院大學「古典文化学事業」伊弉諾神宮ページ"
      }
    ],
    "女性人気ポイント": "「夫婦神の最初の縁結びパワー」という最強の縁結びストーリーが女性に響く。夫婦大楠を一人で抱きしめると縁結びの力が増すという口コミがSNSで拡散中。淡路島の絶景・グルメ（たまねぎ・海鮮）との組み合わせ旅は女性誌でも毎年特集される定番コース。御朱印は直書き対応。",
    "参拝情報": {
      "最寄り駅": "淡路市内のバス停「伊弉諾神宮前」（洲本バスセンターや高速バス停から路線バス）。神戸三宮から高速バス+路線バスで約1時間。または徳島方面から淡路島経由。",
      "駐車場": "境内前に無料駐車場あり（普通車約100台）。",
      "授与所受付時間": "8:30〜17:00（社務所）",
      "御朱印初穂料": "500円"
    },
    "公式URL": "https://kuniuminoshima.jp/",
    "参拝所要時間": "30〜60分",
    "ベストシーズン": {
      "春": "4〜5月の藤の花と新緑の境内が美しい。淡路島の春の花（チューリップ・菜の花）との組み合わせ旅が人気。",
      "夏": "淡路島の海水浴と組み合わせた夏の旅が定番。",
      "秋": "10〜11月の紅葉。淡路島の秋の景色が格別。",
      "冬": "厳粛な冬の参拝。初詣も人気（淡路島最大規模）。"
    },
    "セット参拝コース": [
      "淡路島1日コース：伊弉諾神宮→淡路サービスエリア（たまねぎグルメ）→大鳴門橋展望",
      "国生み聖地コース：伊弉諾神宮→絵島（国生み神話の地）→おのころ島神社"
    ],
    "一人旅アクセス": {
      "電車のみで完結可": false,
      "駅から徒歩可": false,
      "最終アクセス難易度": "中",
      "女性一人歩き安全性コメント": "高速バス+路線バスの組み合わせで訪問可能。淡路島内はバス本数が少ないため時刻表の事前確認が必須。レンタカーが最も効率的。"
    }
  },
  {
    "id": "059",
    "name": "宇倍神社",
    "読み": "うべじんじゃ",
    "旧国": "因幡国",
    "都道府県": "鳥取県",
    "住所": "鳥取県鳥取市国府町宮下651",
    "緯度": 35.5155,
    "経度": 134.2309,
    "創建": "伝：孝徳天皇4年（648年）、因幡国の豪族・射猪葦津比古（いのしあしつひこ）の氏族が亀掛山（かめかけやま）に武内宿禰命を祀ったのが起源とされる。史書上は延長5年（927年）の延喜式神名帳に因幡国名神大社として記載。明治31年（1898年）に現社殿が完成、翌32年（1899年）に日本初・神社の境内が国紙幣（五円紙幣）の図柄に採用された。",
    "主祭神": "武内宿禰命（たけのうちのすくねのみこと）",
    "配祀神": [],
    "ご利益": [
      "長寿",
      "金運・財宝",
      "仕事運・出世",
      "家内安全",
      "縁結び",
      "政治・リーダーシップ"
    ],
    "開運キーワード": "360歳以上生きた「日本最長寿の大臣」を祀る——長寿・金運・出世の神に、人生の豊かさを授けてもらう",
    "開運フード": {
      "name": "鳥取砂丘らっきょう漬け・松葉ガニ料理",
      "店または場所": "鳥取市内の土産店・飲食店。鳥取砂丘周辺の観光施設・鳥取駅前の飲食街。神社から鳥取市中心まで車で約15分。",
      "効能": "らっきょうは解毒・血液浄化の食材として古来から縁起物。松葉ガニは鳥取の最高級食材で、神前にも供えられる「神の恵みの食」。",
      "エピソード": "宇倍神社は武内宿禰命を祀る全国の宇部（宇倍）神社の総本社。明治32年（1899年）に境内の写真が五円紙幣に採用されて以来、昭和時代まで計3種類の日本銀行券の図柄に登場した「お金と縁がある神社」として全国的に知られる。「御縁御守（ごえんおまもり）」は旧五円紙幣の図柄を用いた独自のお守りとして有名。（宇倍神社公式サイト・鳥取県観光連盟参照）"
    },
    "必買お守り": [
      {
        "name": "御縁御守（ごえんおまもり）",
        "初穂料": "社務所にて（要現地確認）",
        "特徴": "旧五円紙幣に宇倍神社の境内が描かれていたことにちなみ、その図柄を活用した「お金と縁のお守り」。「5円＝ご縁」の語呂合わせとも相性がよく、金運・縁結び・仕事運に。宇倍神社公式サイト（ubejinja.or.jp）記載。",
        "どんな人向け": "金運・縁・仕事運アップを願う人"
      },
      {
        "name": "長寿守（ちょうじゅまもり）",
        "初穂料": "社務所にて（要現地確認）",
        "特徴": "武内宿禰命は360歳以上生きた「日本最長寿の人物」として伝わり、長寿の御神徳は全国トップクラス。高齢者・長寿祈願の参拝者に特に人気。",
        "どんな人向け": "長寿を願う人、親・祖父母へのプレゼント"
      },
      {
        "name": "仕事運守（しごとうんまもり）",
        "初穂料": "社務所にて（要現地確認）",
        "特徴": "武内宿禰命は5代の天皇に仕えた「日本最初の大臣」。政治・リーダーシップ・仕事での出世を願う参拝者が多い。",
        "どんな人向け": "昇進・転職・仕事の成功を願う人"
      }
    ],
    "秘密の話": [
      {
        "title": "日本初・神社が国の紙幣図柄になった「お金と縁がある神社」",
        "内容": "明治32年（1899年）4月1日発行の「甲五圓券（五円紙幣）」に、宇倍神社の境内の写真と武内宿禰命の肖像が採用された。全国の神社で最初に日本銀行券の図柄となった神社であり、以後大正・昭和と計3種類の紙幣に登場。「お金の神様の神社」として金運アップを求める参拝者が後を絶たない。",
        "ソース": "宇倍神社公式サイト（ubejinja.or.jp）由緒ページ; 日本銀行鳥取事務所「鳥取とお札のかかわり」（boj.or.jp）"
      },
      {
        "title": "360歳以上生きた「日本最長寿の臣下」武内宿禰——5代の天皇に仕えた伝説的人物",
        "内容": "武内宿禰命は第12代景行天皇から第16代仁徳天皇まで、景行・成務・仲哀・応神・仁徳の5代の天皇に大臣として仕えたとされる。仁徳天皇55年に因幡国（鳥取）の亀掛山で360余歳で亡くなったと伝わり、日本最長寿の人物として長寿信仰の対象となった。",
        "ソース": "宇倍神社公式サイト（ubejinja.or.jp）; Wikipedia「武内宿禰」"
      },
      {
        "title": "因幡の白兎神話の地・鳥取に鎮座する一の宮",
        "内容": "宇倍神社が鎮座する鳥取市の周辺は、古事記の「因幡の白兎（いなばのしろうさぎ）」神話の舞台。大国主命（=武内宿禰命が仕えた時代の神）が因幡の白兎を助けた地として、白兎神社（鳥取市）など関連スポットが多数存在する。宇倍神社参拝と「因幡の白兎」神話の地巡りを組み合わせた「古事記聖地旅」が女性に人気。",
        "ソース": "鳥取県観光連盟「宇倍神社」（tottori-guide.jp）; 因幡万葉歴史館「宇倍神社」ページ"
      }
    ],
    "女性人気ポイント": "「日本初・紙幣になった神社」というユニークな肩書が話題。御縁御守は金運アップのお守りとして女性に人気。因幡の白兎神話の地・鳥取を巡る古事記女子旅の定番スポット。鳥取砂丘・白兎神社との組み合わせで鳥取1日旅が充実する。御朱印は社務所にて授与。",
    "参拝情報": {
      "最寄り駅": "JR因美線「国府駅（こうえき）」より徒歩約15分。JR鳥取駅からタクシーで約20分。または鳥取駅から路線バス（日ノ丸バス「宇倍神社前」）。",
      "駐車場": "無料駐車場あり。",
      "授与所受付時間": "9:00〜16:00（社務所）",
      "御朱印初穂料": "300円"
    },
    "公式URL": "https://www.ubejinja.or.jp/",
    "参拝所要時間": "20〜30分",
    "ベストシーズン": {
      "春": "4〜5月の桜。境内の桜は地域の花見スポットとしても知られる。",
      "夏": "山陰の夏は比較的涼しく参拝しやすい。",
      "秋": "10〜11月の紅葉。但馬牛や松葉ガニ解禁と重なる美食シーズン。",
      "冬": "松葉ガニシーズン（11〜3月）。鳥取砂丘の冬景色との組み合わせ。"
    },
    "セット参拝コース": [
      "鳥取2社コース：宇倍神社→（車1時間）→倭文神社（湯梨浜）",
      "鳥取古事記コース：宇倍神社→白兎神社（因幡の白兎）→鳥取砂丘"
    ],
    "一人旅アクセス": {
      "電車のみで完結可": true,
      "駅から徒歩可": true,
      "最終アクセス難易度": "中",
      "女性一人歩き安全性コメント": "国府駅から15分の徒歩ルートは住宅街で安全。バスを使う場合は本数が少ないため時刻表の確認が必要。"
    }
  },
  {
    "id": "060",
    "name": "倭文神社",
    "読み": "しとりじんじゃ",
    "旧国": "伯耆国",
    "都道府県": "鳥取県",
    "住所": "鳥取県東伯郡湯梨浜町大字宮内754",
    "緯度": 35.4873,
    "経度": 133.8892,
    "創建": "創立年代不詳。由緒口伝によれば、当地方の主産業が倭文（しづおり）の織物であったことから、倭文の祖神・建葉槌命を祀ったのが起源とされる。史書上は斉衡3年（856年）の『文徳実録』に「伯耆国倭文神従五位上」、延長5年（927年）の延喜式神名帳に「伯耆国川村郡倭文神社」として記載。",
    "主祭神": "建葉槌命（たけはづちのみこと）",
    "配祀神": [
      "下照姫命（したてるひめのみこと）",
      "大国主命（おおくにぬしのみこと）",
      "少彦名命（すくなひこなのみこと）ほか計7柱"
    ],
    "ご利益": [
      "安産（特に著名）",
      "縁結び",
      "機織り・技芸上達",
      "長寿",
      "家内安全"
    ],
    "開運キーワード": "東郷湖の湖畔の高台に鎮まる「安産の神」——織物の祖神が授ける、命をつなぐ縁の力",
    "開運フード": {
      "name": "東郷湖のしじみ汁・梨（二十世紀梨）",
      "店または場所": "湯梨浜町の道の駅「はわい」（東伯郡湯梨浜町羽合87）または東郷湖周辺の飲食店。神社から車で約10分。",
      "効能": "東郷湖のしじみは山陰の名産品で、肝臓・解毒・長寿のスーパーフード。二十世紀梨は鳥取の代名詞で「実り・豊穣・縁起」の象徴。",
      "エピソード": "倭文神社は東郷湖（湯梨浜）の北東の御冠山（みかむりやま）の中腹に鎮座し、湖を見下ろす独特のロケーションが美しい。「安産の神」として境内には「安産岩」と呼ばれる岩があり、全国から安産祈願の参拝者が訪れる。伯耆国一の宮として数少ない「静謐な穴場一の宮」。（倭文神社公式サイト・鳥取観光連盟参照）"
    },
    "必買お守り": [
      {
        "name": "安産守（あんざんまもり）",
        "初穂料": "社務所にて（要現地確認・祈祷料5,000円より）",
        "特徴": "下照姫命は安産の神として信仰が厚く、全国から安産祈願のお参りがある。伯耆国一の宮の安産守りとして格式がある。倭文神社公式サイト（sitorijinja.com）記載。",
        "どんな人向け": "妊婦・子授けを願う女性"
      },
      {
        "name": "縁結守（えんむすびまもり）",
        "初穂料": "社務所にて（要現地確認）",
        "特徴": "下照姫命は大国主命の娘で、縁結びの御神徳も持つ。夫婦神話との関連から良縁・夫婦円満の守りとしても授与される。",
        "どんな人向け": "良縁・夫婦円満を願う女性"
      },
      {
        "name": "技芸上達守（ぎげいじょうたつまもり）",
        "初穂料": "社務所にて（要現地確認）",
        "特徴": "建葉槌命は「倭文（しづおり）の祖神」——織物・手仕事の神様。裁縫・手芸・伝統工芸など技芸全般の上達を願う珍しいお守り。",
        "どんな人向け": "手仕事・手芸・伝統工芸に取り組む女性"
      }
    ],
    "秘密の話": [
      {
        "title": "「倭文（しづおり）」——古代の織物産業が生み出した神社名の由来",
        "内容": "「倭文」とは日本古来の織物（しづおり布）のことで、麻や木綿の繊維を縦横に細かく縫い込んだ独特の布。当地方で古代から盛んだったこの織物産業の守護神として建葉槌命が祀られた。倭文の織物産業が衰退した後は、下照姫命への安産信仰が主流となり現代に至る。日本の「繊維産業の原点」に関わる神社名は全国に倭文神社が複数存在するが、伯耆国一の宮がその代表格。",
        "ソース": "倭文神社Wikipedia（湯梨浜町）; 鳥取県神社庁「倭文神社由緒」（tottori-jinjacho.jp）"
      },
      {
        "title": "「安産岩」——境内に現存する自然石で安産を祈願する古来の慣わし",
        "内容": "境内には「安産岩」と呼ばれる自然の岩があり、下照姫命の安産の御神徳と結びついた参拝の慣わしが伝わる。下照姫命は大国主命の娘として古事記に登場し、出産に関わる神話的背景を持つことから安産信仰が発展した。",
        "ソース": "倭文神社公式ブログ（sidorijinja.com）; 安産の神様 倭文神社ページ（sitorijinja.com）"
      },
      {
        "title": "東郷湖を見下ろす御冠山の中腹——湖と杜が織りなす絶景の「隠れ一の宮」",
        "内容": "倭文神社は東郷湖の湖畔から山道を上った御冠山（みかむりやま）の中腹に鎮座し、境内から東郷湖と鳥取の里山を見渡せる絶景スポット。全国的な知名度は低いが、「静謐な穴場の一の宮」として御朱印愛好者や女性参拝者の間でじわじわと人気が高まっている。",
        "ソース": "鳥取中部癒しの旅紀行「倭文神社」（tottori-iyashitabi.com）; 鳥取県観光連盟「倭文神社」"
      }
    ],
    "女性人気ポイント": "東郷湖を見下ろす静寂な境内は「自分だけの神社」的な穴場感が女性に響く。安産守りは全国的に知られており、妊婦・子授けを願う女性の参拝が絶えない。手仕事・手芸の神としての「技芸上達守り」は編み物・裁縫女子にマニアックな人気。御朱印は社務所にて。",
    "参拝情報": {
      "最寄り駅": "JR山陰本線「松崎駅」から徒歩約35分またはタクシーで約10分。車：山陰道「湯梨浜IC」から約10分。",
      "駐車場": "境内前に無料駐車場あり。",
      "授与所受付時間": "9:30〜15:30（社務所）",
      "御朱印初穂料": "社務所にて（要現地確認）"
    },
    "公式URL": "https://www.sitorijinja.com/",
    "参拝所要時間": "20〜30分",
    "ベストシーズン": {
      "春": "4〜5月の東郷湖と新緑の眺望が美しい。",
      "夏": "東郷温泉（湯梨浜）と組み合わせた夏の温泉旅に最適。",
      "秋": "10月の二十世紀梨の収穫シーズン。倭文神社→梨の直売所の秋コースが女性に人気。",
      "冬": "しじみ汁が美味しい冬の東郷湖畔参拝。静寂の山上神社。"
    },
    "セット参拝コース": [
      "伯耆・因幡2社コース：倭文神社（湯梨浜）→（車1時間）→宇倍神社（鳥取市）",
      "湯梨浜温泉コース：倭文神社→東郷温泉（湯梨浜町）→道の駅「はわい」梨グルメ"
    ],
    "一人旅アクセス": {
      "電車のみで完結可": false,
      "駅から徒歩可": false,
      "最終アクセス難易度": "難",
      "女性一人歩き安全性コメント": "松崎駅から山道を35分歩くのは難しいため、タクシーまたはレンタカー推奨。東郷温泉の宿泊者向けの送迎サービスを利用する方法もある。"
    }
  },
  {
    "id": "061",
    "name": "出雲大社",
    "読み": "いづもおおやしろ",
    "旧国": "出雲国",
    "都道府県": "島根県",
    "住所": "島根県出雲市大社町杵築東195",
    "緯度": 35.4017,
    "経度": 132.6851,
    "創建": "伝：『古事記』・『日本書紀』の「国譲り神話」に由緒が記される日本最古の神社のひとつ。大国主大神が国土を天照大御神に譲った際に「私が鎮まる壮大な宮殿を建てよ」と申された場所とされる。現在の本殿（国宝）は延享元年（1744年）造営。古代には高さ48mの巨大社殿が存在したとされる（2000年に境内で古代柱の遺構を発掘・確認）。",
    "主祭神": "大国主大神（おおくにぬしのおおかみ）、別名：大黒様（だいこくさま）",
    "配祀神": [
      "天穂日命（あめのほひのみこと）",
      "天夷鳥命（あめのひなとりのみこと）",
      "国土神（くにつかみ）等の多数の神々"
    ],
    "ご利益": [
      "縁結び（日本最強）",
      "夫婦円満・恋愛成就",
      "縁切り・悪縁断ち",
      "家内安全",
      "商売繁昌",
      "農業守護",
      "人間の縁全般（家族・友人・仕事の縁も含む）"
    ],
    "開運キーワード": "旧暦10月に全国の神々が集まる「縁の最高司令塔」——縁結びの神話の本家で、人生のすべての縁を整える",
    "開運フード": {
      "name": "出雲ぜんざい（じんざいもち発祥）と出雲そば",
      "店または場所": "【ぜんざい】神門通り（かみかどどおり）の「日本ぜんざい学会壱号店」（出雲市大社町杵築南837-2）・「ご縁横丁」各店。【出雲そば】神門通りや出雲大社周辺の出雲そば専門店多数（「荒木屋」「かねや」など）。",
      "効能": "出雲ぜんざいは「神在月に神在餅（じんざいもち）として振る舞われたのが全国に広まった」とされる日本のぜんざい発祥の地。出雲そば（割子そば）は「三大そば」のひとつ。どちらも縁結びの神様への奉納食が原点。",
      "エピソード": "神門通りは出雲大社の勢溜（せいだまり）から約700m続く門前町。出雲そば・ぜんざい・縁結びグッズ・島根の銘菓が揃い、参拝前後の食べ歩きとショッピングが充実。（出雲大社公式サイト・出雲観光協会参照）"
    },
    "必買お守り": [
      {
        "name": "縁結守（えんむすびまもり）",
        "初穂料": "1,000円",
        "特徴": "大国主大神の縁結びの御神徳を宿す出雲大社の代表的なお守り。赤・白・青・黄など複数色展開。全国の出雲大社分祠でも購入できるが、本社で授かることに特別な意味がある。出雲大社公式サイト・御守所記載。",
        "どんな人向け": "縁結びを願うすべての女性、日本で一番有名な縁結び守り"
      },
      {
        "name": "縁結びの糸（えんむすびのいと）",
        "初穂料": "1,000円",
        "特徴": "出雲大社限定の赤い糸のお守り。「赤い糸で縁が結ばれる」という伝承に基づく。お守りに封入された赤い糸は神前で祈祷されたもの。SNSで「出雲の赤い糸」として絶大な知名度を誇る。出雲大社公式サイト記載。",
        "どんな人向け": "縁結びを強く願う女性、特別な想いを持つ人"
      },
      {
        "name": "身体健全守（しんたいけんぜんまもり）",
        "初穂料": "1,000円",
        "特徴": "大国主大神の「医薬の神」としての側面を宿す健康守り。縁結び守りと合わせて2種購入する参拝者が多い。出雲大社公式サイト・御守所記載。",
        "どんな人向け": "健康・病気平癒を願う人、家族への贈り物"
      },
      {
        "name": "学業守（がくぎょうまもり）",
        "初穂料": "1,000円",
        "特徴": "大国主大神の「知恵の神」としての御神徳を宿す。受験生に人気。出雲大社公式サイト記載。",
        "どんな人向け": "受験生・資格試験を控えた人"
      }
    ],
    "秘密の話": [
      {
        "title": "参拝は「二礼四拍手一礼」——全国の神社と異なる出雲大社独自の作法",
        "内容": "一般的な神社の参拝作法は「二礼二拍手一礼」だが、出雲大社では「二礼四拍手一礼」が正式作法。4拍手は年に一度の最大祭典（5月14日の例祭）では8拍手が行われ、「8」は古来より無限を意味する数。日常の4拍手はその半分で「限りない拍手を略したもの」とされる。知らずに二拍手する参拝者も多いが、四拍手が正しい。",
        "ソース": "出雲大社公式サイト「よくあるご質問・参拝方法」（izumooyashiro.or.jp）; 島根県観光サイト「参拝方法と周辺情報」"
      },
      {
        "title": "御本殿の御神座は「西向き」——大国主大神が西を向く謎",
        "内容": "出雲大社の本殿は南向きだが、内部の御神座（大国主大神の御座所）は「西向き」に設置されている。なぜ西を向くかは諸説あり、①稲佐の浜から来る八百万の神々を迎えるため、②古代に西から来た疫病を防ぐ医神の向き、③大社造の建築様式の特性による結果——などが挙げられているが、「真の理由は謎のまま」というのが現状。この謎が出雲大社を神秘的にしている。",
        "ソース": "出雲大社公式サイト「御本殿」ページ（izumooyashiro.or.jp）; DiscoverJapan「出雲大社の建築」記事; 出雲大社縁結び文化研究所サイト"
      },
      {
        "title": "「ぜんざい発祥の地」は出雲——神在月に振る舞った「じんざいもち」が全国へ",
        "内容": "旧暦10月（神在月）に出雲で全国の神々に振る舞われた餅菓子「神在餅（じんざいもち）」が、出雲弁のズーズー弁で「ずんざい」→「ぜんざい」と訛り、京都に伝わって全国に広まったとされる。現在も出雲ではぜんざいを「発祥の食」として大切にしており、神門通りには専門店が多数。日本のぜんざい文化の起源が出雲にあるとは、多くの人が知らない事実。",
        "ソース": "出雲ぜんざい学会「ぜんざいの歴史」（1031-zenzai.com）; BRUTUS.jp「ぜんざい発祥地、出雲の国」; 島根県観光サイト"
      },
      {
        "title": "古代の本殿は「高さ48m」——2000年に発掘された巨大柱の遺構",
        "内容": "現在の本殿の高さは約24mだが、古代（平安時代）には高さ48m（一説では96m）の巨大な社殿が存在したとされてきた。この伝説は長らく「神話の誇張」と思われていたが、2000年（平成12年）の境内発掘調査で直径1.3mの丸太3本を1組にした巨大な柱の遺構が発見され、古代の巨大社殿の実在が証明された。現在レプリカが島根県立古代出雲歴史博物館に展示されている。",
        "ソース": "出雲大社公式サイト; 島根県立古代出雲歴史博物館公式サイト（izm.ed.jp）; nippon.com「出雲大社60年ぶりの大遷宮」"
      }
    ],
    "女性人気ポイント": "日本最強の縁結び聖地として女性参拝者数全国トップクラス。「縁結びの糸」はプレゼントとしても絶大な人気。神門通りでの食べ歩き（ぜんざい・出雲そば）は参拝旅の定番コース。旧暦10月の神在祭（神在月）は全国の神々が集まる特別期間として女性誌・SNSで毎年話題に。御朱印は4種類（本殿・素鵞社・神楽殿・授与所）で御朱印ガールに大人気。島根観光の中心地として、稲佐の浜・古代出雲歴史博物館との組み合わせ旅も充実。",
    "参拝情報": {
      "最寄り駅": "一畑電車「出雲大社前駅」より徒歩約7分。JR「出雲市駅」から一畑バスで約25分「正門前」下車。大阪から特急「やくも」+一畑電車で約3時間40分。",
      "駐車場": "境内周辺に複数の無料・有料駐車場あり。神在祭・初詣時期は大渋滞のため公共交通機関推奨。",
      "授与所受付時間": "6:00〜19:00（お守り所・御守所）",
      "御朱印初穂料": "500円（各授与所）"
    },
    "公式URL": "https://izumooyashiro.or.jp/",
    "参拝所要時間": "60〜90分（境内全体を丁寧に参拝する場合。神門通り食べ歩きを加えると半日〜1日）",
    "ベストシーズン": {
      "春": "3〜5月の新緑と桜。観光客が比較的少なく境内もゆっくり参拝できる。",
      "夏": "7〜8月は混雑するが島根の夏祭りと組み合わせた旅が楽しい。",
      "秋": "旧暦10月（新暦では11月頃）の神在月・神在祭が最大のシーズン。全国の神が集まる特別な時期。紅葉も美しい。",
      "冬": "松葉ガニシーズン（11〜3月）との組み合わせ旅。静寂な境内での初詣も人気。"
    },
    "セット参拝コース": [
      "出雲国2社コース：出雲大社→（車40分）→熊野大社（松江市）",
      "出雲神話聖地コース：出雲大社→稲佐の浜（神迎の道）→古代出雲歴史博物館",
      "島根1泊2日コース：出雲大社（1日目）→玉造温泉泊→松江城・熊野大社（2日目）"
    ],
    "一人旅アクセス": {
      "電車のみで完結可": true,
      "駅から徒歩可": true,
      "最終アクセス難易度": "易",
      "女性一人歩き安全性コメント": "一畑電車「出雲大社前駅」から境内まで7分。神門通りは観光地として整備され日中は安全。食べ歩きも一人で楽しめる環境。夜間の一人歩きは避けることを推奨。"
    }
  },
  {
    "id": "062",
    "name": "熊野大社",
    "読み": "くまのたいしゃ",
    "旧国": "出雲国",
    "都道府県": "島根県",
    "住所": "島根県松江市八雲町熊野2451",
    "緯度": 35.355,
    "経度": 133.173,
    "創建": "伝：神代の昔に素盞嗚尊が最初に火を起こした地として「日本火出初之社（ひのもとひでぞめのやしろ）」と称される。史書上は延長5年（927年）の延喜式神名帳に出雲国名神大社として記載。出雲大社と並ぶ出雲国一の宮として「出雲の二大一宮」。",
    "主祭神": "神祖熊野大神櫛御気野命（かむろぎくまのおおかみくしみけぬのみこと）別名：素盞嗚尊（すさのおのみこと）",
    "配祀神": [],
    "ご利益": [
      "縁結び",
      "厄除け",
      "商売繁昌",
      "火の神のパワー・創造力",
      "縁切り",
      "家内安全"
    ],
    "開運キーワード": "日本で最初に火を起こした神・素盞嗚尊の社——火のパワーで人生を新たに燃やし直す創造の聖地",
    "開運フード": {
      "name": "出雲そば（割り子そば）・松江の和菓子（不昧公御好み菓子）",
      "店または場所": "熊野大社周辺には専門の飲食店はないが、松江市中心部（車で約40分）に出雲そばの名店多数。松江市は「和菓子の城下町」として有名で、不昧公（松平治郷）にちなむ和菓子文化が発達。「彩雲堂」「風流堂」など松江の老舗和菓子店。",
      "効能": "出雲そばは「三大そば」のひとつで、割り子そばは松江城下町が発祥とも。松江の和菓子は「茶の湯の文化」と結びつき、食べることで心が整うとされる。",
      "エピソード": "熊野大社は島根県最大の川・斐伊川（ひいかわ）の源流近くに鎮座。出雲大社から車で約40分という距離で、「出雲国2社巡り」の定番コース。毎年10月15日の「鑽火祭（さんかさい）」は出雲大社の宮司が参向し「亀太夫神事」として奉仕する、全国でも特異な神事。（熊野大社公式サイト・松江観光協会参照）"
    },
    "必買お守り": [
      {
        "name": "縁結守（えんむすびまもり）・くしのかみ守り",
        "初穂料": "社務所にて（要現地確認）",
        "特徴": "熊野大社の独自の縁結びお守り。素盞嗚尊は出雲系の縁結びの神として大国主命（出雲大社）との二神信仰がある。",
        "どんな人向け": "良縁を願う女性・出雲大社と合わせて二社で縁結びを完成させたい人"
      },
      {
        "name": "やくも塗り携帯ストラップ（縁結び）",
        "初穂料": "社務所にて（要現地確認）",
        "特徴": "松江・雲南の伝統工芸「出雲漆器（やくも塗り）」を使った縁結びストラップ。漆器の美しい黒と朱の表面が人気。熊野大社社務所にて授与。",
        "どんな人向け": "伝統工芸好きの女性・特別感のあるお守りを求める人"
      },
      {
        "name": "厄除守（やくよけまもり）",
        "初穂料": "社務所にて（要現地確認）",
        "特徴": "素盞嗚尊は八岐大蛇（ヤマタノオロチ）を退治した「厄払いの英雄神」。厄除け・邪気払いの御神徳が特に強い。",
        "どんな人向け": "厄年の人・災難から身を守りたい人"
      }
    ],
    "秘密の話": [
      {
        "title": "毎年10月15日の「亀太夫神事」——出雲大社宮司が参向して餅の出来に苦情を言う全国唯一の神事",
        "内容": "毎年10月15日の「鑽火祭（さんかさい）」では、出雲大社の宮司が熊野大社に参向し、火起こし道具（燧臼・燧杵）を受け取る。その際、熊野大社の神職が出雲大社から納められた餅の出来ばえについて「色が悪い」「形が悪い」と口やかましく苦情を言い立てる「亀太夫神事」が執り行われる。神職が「苦情を言う」という全国でも他に例を見ない珍しい神事で、神話時代からの出雲大社との上下関係を今に伝える。",
        "ソース": "熊野大社公式サイト（kumanotaisha.or.jp）; 松江観光協会「鑽火祭・御櫛祭」（kankou-matsue.jp）"
      },
      {
        "title": "「日本で最初に火を起こした場所」——鑽火殿に保管される火起こし道具",
        "内容": "熊野大社の境内には「鑽火殿（さんかでん）」があり、素盞嗚尊が日本で最初に火を起こしたとされる神器「燧臼（ひきりうす）」と「燧杵（ひきりきね）」が保管されている。毎年これが出雲大社に渡され、11月23日の「古伝新嘗祭」の神聖な火として使われる。「日本の火の発祥地」として「日本火出初之社」の別名を持つ。",
        "ソース": "熊野大社公式サイト（kumanotaisha.or.jp）; 出雲神話ゆかりの地「熊野大社」（izumo-shinwa.com）; 神仏霊場会「第十五番熊野大社」"
      },
      {
        "title": "出雲大社と「対の一宮」——2,000年にわたって出雲国の2大聖地として崇敬された関係",
        "内容": "出雲大社（杵築大社）と熊野大社は、古代から出雲国の2大一宮として対をなしてきた。出雲大社が縁結び・農業の神（大国主命）を祀るのに対し、熊野大社は火の神・厄払いの神（素盞嗚尊）を祀る。古事記・日本書紀の神話では素盞嗚尊が大国主命の父系の祖先神にあたり、「父の神社から息子の神社へ」という神話的なつながりで両社は深く結ばれている。",
        "ソース": "熊野大社Wikipedia; 島根浪漫旅「出雲大社と熊野大社」（izumo-shinwa.com）; 理系脳で紐解く日本古代史「出雲大社と熊野大社」"
      }
    ],
    "女性人気ポイント": "出雲大社との「2社セット参拝」で「縁結びのダブルパワー」を得る旅として女性に人気急上昇。やくも塗りのお守りは「島根でしか買えない工芸お守り」として人気。「亀太夫神事」の珍しさが口コミで広がり、参拝動機になっている。松江の和菓子・宍道湖のしじみ汁との組み合わせで島根グルメも充実。御朱印は社務所にて。",
    "参拝情報": {
      "最寄り駅": "JR木次線「出雲八代（いずもやしろ）駅」から徒歩約40分またはタクシーで約10分。松江駅から車で約40分または一畑バス（要乗継・約1時間）。出雲大社からは車で約40分。",
      "駐車場": "境内前に無料駐車場あり。",
      "授与所受付時間": "9:00〜16:30（社務所）",
      "御朱印初穂料": "500円"
    },
    "公式URL": "http://www.kumanotaisha.or.jp/",
    "参拝所要時間": "30〜45分",
    "ベストシーズン": {
      "春": "5月の斐伊川沿いの新緑と参拝が清々しい。",
      "夏": "出雲神話の地を巡る夏旅の拠点として。",
      "秋": "10月15日の鑽火祭・亀太夫神事（非公開神事だが雰囲気を感じに）。11〜3月の松葉ガニシーズン。",
      "冬": "静寂の境内での参拝。松葉ガニと出雲そばを楽しむ島根冬旅。"
    },
    "セット参拝コース": [
      "出雲国2社コース：熊野大社（午前）→（車40分）→出雲大社（午後）",
      "松江観光コース：熊野大社→松江城（宍道湖）→玉造温泉（宿泊）"
    ],
    "一人旅アクセス": {
      "電車のみで完結可": false,
      "駅から徒歩可": false,
      "最終アクセス難易度": "難",
      "女性一人歩き安全性コメント": "公共交通機関のみでのアクセスは難しい。出雲大社参拝後にレンタカーで訪問するか、松江発のタクシー観光コースを利用するのが最も効率的。"
    }
  }
]